Workbook

Sheet Test Cases
A1: TC-ID | B1: Category | C1: Feature | D1: Test Case Title | E1: Preconditions | F1: Test Steps | G1: Expected Result | H1: Priority | I1: Implementation Status | J1: Notes | K1: URL | L1: Pass Status | M1: Link | N1: Notes | O1: Spec Ref
A2: TC-SUB-001 | B2: Submission | C2: Form Fields | D2: Submit ringi with all required fields | E2: User logged in as employee | F2: 1. Navigate to the app URL 2. Click 'New Submission' button 3. Fill in Title: 'Office Supplies Purchase' 4. Select Category: 'Purchasing' 5. Enter Vendor Name: 'ABC Corp' 6. Add item: Name='Printer', Qty=2, Amount=50000 7. Select Priority: 'High' 8. Set Required By Date 9. Enter Department: 'Engineering' 10. Enter Reason for Purchase 11. Enter Purpose 12. Click Submit | G2: Ringi created with status 'Pending'. Card appears in dashboard list. Activity log records the creation. | H2: P1 | I2: Implemented | J2: Core submission flow works with current form fields | K2: https://eb-filemg-development.vercel.app | L2: N/A | O2: Spec 6.1 (Submission) → "Form fields: Subject, Category (Purchasing, Contracts, Expenses, Misc.), Amount (tax incl./excl.), Tax category, Payment terms, Vendor/Counterparty, Purpose, Period, Budget code, Project, Desired approval date, Applicant/Department."
A3: TC-SUB-002 | B3: Submission | C3: Tax Calculation | D3: Submit ringi with tax-inclusive calculation | E3: User logged in, category is Purchasing | F3: 1. Click 'New Submission' 2. Select Category: 'Purchasing' 3. Toggle 'Use Tax' ON 4. Toggle 'Tax Included' 5. Enter Tax Rate: 10% 6. Add item: Amount=110000 7. Fill remaining required fields 8. Click Submit | G3: Tax calculated correctly. Amount displays with tax-inclusive label. Total reflects tax calculation. | H3: P2 | I3: Implemented | J3: Tax toggle only shows for Purchasing category | K3: https://eb-filemg-development.vercel.app | L3: N/A | O3: Spec 6.1 (Submission) → "Form fields: Subject, Category (Purchasing, Contracts, Expenses, Misc.), Amount (tax incl./excl.), Tax category, Payment terms, Vendor/Counterparty, Purpose, Period, Budget code, Project, Desired approval date, Applicant/Department."
A4: TC-SUB-003 | B4: Submission | C4: Tax Calculation | D4: Submit ringi with tax-exclusive calculation | E4: User logged in, category is Purchasing | F4: 1. Click 'New Submission' 2. Select Category: 'Purchasing' 3. Toggle 'Use Tax' ON 4. Toggle 'Tax Excluded' 5. Enter Tax Rate: 10% 6. Add item: Amount=100000 7. Fill remaining required fields 8. Click Submit | G4: Tax calculated on top of amount. Display shows tax-exclusive amount + tax = total. | H4: P2 | I4: Implemented | J4: Tax-exclusive adds tax on top of base amount | K4: https://eb-filemg-development.vercel.app | L4: N/A | O4: Spec 6.1 (Submission) → "Form fields: Subject, Category (Purchasing, Contracts, Expenses, Misc.), Amount (tax incl./excl.), Tax category, Payment terms, Vendor/Counterparty, Purpose, Period, Budget code, Project, Desired approval date, Applicant/Department."
A5: TC-SUB-004 | B5: Submission | C5: Line Items | D5: Submit ringi with multiple line items | E5: User logged in | F5: 1. Click 'New Submission' 2. Fill required fields 3. Add Item 1: 'Laptop', Qty=5, Amount=200000 4. Click 'Add Item' 5. Add Item 2: 'Mouse', Qty=5, Amount=5000 6. Click 'Add Item' 7. Add Item 3: 'Keyboard', Qty=5, Amount=8000 8. Verify total auto-calculates 9. Click Submit | G5: All 3 items saved. Total amount = (200000x5 + 5000x5 + 8000x5) = 1,065,000. Items table displays correctly on detail page. | H5: P2 | I5: Implemented | J5: Items stored as JSONB array | K5: https://eb-filemg-development.vercel.app | L5: N/A | O5: Spec 6.1 (Submission) → "Form fields: Subject, Category (Purchasing, Contracts, Expenses, Misc.), Amount (tax incl./excl.), Tax category, Payment terms, Vendor/Counterparty, Purpose, Period, Budget code, Project, Desired approval date, Applicant/Department."
A6: TC-SUB-005 | B6: Submission | C6: Validation | D6: Submit ringi with missing required fields | E6: User logged in | F6: 1. Click 'New Submission' 2. Leave Title empty 3. Leave Vendor Name empty 4. Do not add any items 5. Click Submit | G6: Form validation errors shown for all required fields. Submission is blocked. Error messages in current language (EN/JA). | H6: P1 | I6: Implemented | J6: Yup validation schema enforces required fields | K6: https://eb-filemg-development.vercel.app | L6: N/A | O6: Spec 6.1 (Submission) → "Form fields: Subject, Category (Purchasing, Contracts, Expenses, Misc.), Amount (tax incl./excl.), Tax category, Payment terms, Vendor/Counterparty, Purpose, Period, Budget code, Project, Desired approval date, Applicant/Department."
A7: TC-SUB-006 | B7: Submission | C7: Attachments | D7: Submit ringi with document attachments | E7: User logged in, documents exist in system | F7: 1. Click 'New Submission' 2. Fill all required fields 3. In attachments section, upload a PDF file 4. Upload a second image file 5. Click Submit 6. Navigate to detail page | G7: Both attachments linked to the ringi. File cards display on detail page with download links. | H7: P2 | I7: Implemented | J7: Uses approval_request_documents junction table | K7: https://eb-filemg-development.vercel.app | L7: N/A | O7: Spec 6.1 (Submission) → "Attachments: Quotes, contracts, and related materials. No tampering allowed after approval (must re-apply as a new version)."
A8: TC-SUB-008 | B8: Submission | C8: Form Fields | D8: Verify budget_code field exists in form | E8: User logged in | F8: 1. Click 'New Submission' 2. Look for 'Budget Code' field in the form 3. Enter a budget code value | G8: Budget Code field present and fillable. Value saved with ringi. | H8: P3 | I8: Not Yet Implemented | J8: Spec section 8 requires budget_code. Not in current schema. | K8: https://eb-filemg-development.vercel.app | L8: N/A | O8: Spec 6.1 (Submission) → "Form fields: Subject, Category (Purchasing, Contracts, Expenses, Misc.), Amount (tax incl./excl.), Tax category, Payment terms, Vendor/Counterparty, Purpose, Period, Budget code, Project, Desired approval date, Applicant/Department."
A9: TC-SUB-009 | B9: Submission | C9: Form Fields | D9: Verify project_code field exists in form | E9: User logged in | F9: 1. Click 'New Submission' 2. Look for 'Project Code' field in the form 3. Enter a project code value | G9: Project Code field present and fillable. Value saved with ringi. | H9: P3 | I9: Not Yet Implemented | J9: Spec section 8 requires project_code. Not in current schema. | K9: https://eb-filemg-development.vercel.app | L9: N/A | O9: Spec 6.1 (Submission) → "Form fields: Subject, Category (Purchasing, Contracts, Expenses, Misc.), Amount (tax incl./excl.), Tax category, Payment terms, Vendor/Counterparty, Purpose, Period, Budget code, Project, Desired approval date, Applicant/Department."
A10: TC-SUB-010 | B10: Submission | C10: Form Fields | D10: Verify currency field exists in form | E10: User logged in | F10: 1. Click 'New Submission' 2. Look for 'Currency' selector in the form 3. Select different currencies (JPY, USD, etc.) | G10: Currency field present with options (JPY, USD, etc.). Selected currency saved with ringi. | H10: P3 | I10: Not Yet Implemented | J10: Spec section 8 requires currency. Not in current schema. | K10: https://eb-filemg-development.vercel.app | L10: N/A | O10: Spec 6.1 (Submission) → "Form fields: Subject, Category (Purchasing, Contracts, Expenses, Misc.), Amount (tax incl./excl.), Tax category, Payment terms, Vendor/Counterparty, Purpose, Period, Budget code, Project, Desired approval date, Applicant/Department."
A11: TC-SUB-011 | B11: Submission | C11: Form Fields | D11: Verify start_date and end_date (period) fields | E11: User logged in | F11: 1. Click 'New Submission' 2. Look for 'Start Date' and 'End Date' (Period) fields 3. Set both dates | G11: Both start and end date fields present for period specification. Values saved. | H11: P3 | I11: Not Yet Implemented | J11: Current code has single 'date' field. Spec requires start_date and end_date. | K11: https://eb-filemg-development.vercel.app | L11: N/A | O11: Spec 6.1 (Submission) → "Form fields: Subject, Category (Purchasing, Contracts, Expenses, Misc.), Amount (tax incl./excl.), Tax category, Payment terms, Vendor/Counterparty, Purpose, Period, Budget code, Project, Desired approval date, Applicant/Department."
A12: TC-SUB-012 | B12: Submission | C12: Form Fields | D12: Verify desired_approval_date field | E12: User logged in | F12: 1. Click 'New Submission' 2. Look for 'Desired Approval Date' field 3. Select a date | G12: Desired approval date field present and selectable. Value saved with ringi. | H12: P3 | I12: Not Yet Implemented | J12: Spec section 8 requires desired_approval_date. Not in current schema. | K12: https://eb-filemg-development.vercel.app | L12: N/A | O12: Spec 6.1 (Submission) → "Form fields: Subject, Category (Purchasing, Contracts, Expenses, Misc.), Amount (tax incl./excl.), Tax category, Payment terms, Vendor/Counterparty, Purpose, Period, Budget code, Project, Desired approval date, Applicant/Department."
A13: TC-SUB-013 | B13: Submission | C13: Draft | D13: Save ringi as draft | E13: User logged in | F13: 1. Click 'New Submission' 2. Fill some fields partially 3. Click 'Save as Draft' 4. Verify status shows 'Draft' 5. Return later and edit the draft 6. Submit the draft | G13: Ringi saved with status 'Draft'. Appears in dashboard with Draft badge. Not visible to approvers. Can be edited and submitted later. | H13: P2 | I13: Not Yet Implemented | J13: No 'draft' status in current system. Spec requires Draft as initial state. | K13: https://eb-filemg-development.vercel.app | L13: N/A | O13: Spec 6.1 (Submission) → "Statuses: Draft / Applying / Waiting for Approval (by stage) / Sent Back / Rejected / Approved / Expired."
... A108: TC-PDF-003 | B108: PDF Generation | C108: S3 Storage | D108: Verify PDF stored in S3 with metadata tags | E108: Completion PDF generated | F108: 1. Check S3 bucket for generated PDF 2. Verify metadata tags applied (ringi_id, category, department, approved_date) 3. Verify S3 object key follows naming convention | G108: PDF stored in S3 with proper metadata tags. Accessible via presigned URL. | H108: P3 | I108: Not Yet Implemented | J108: No S3 metadata tagging for completion PDFs. | K108: https://eb-filemg-development.vercel.app | L108: N/A | O108: Spec 6.3 (Approval Operations) → "Completed Ringi PDF and attachments are stored in S3 with metadata."

Sheet Summary
A1: Test Cases — Spec Implementation Coverage
A2: Category | B2: Total | C2: Implemented | D2: Partial | E2: Not Yet | F2: Coverage %
A3: Submission | B3: =COUNTIF('Test Cases'!B:B,A3) | C3: =COUNTIFS('Test Cases'!B:B,A3,'Test Cases'!I:I,"Implemented") | D3: =COUNTIFS('Test Cases'!B:B,A3,'Test Cases'!I:I,"Partially Implemented") | E3: =B3-C3-D3 | F3: =IF(B3=0,0,(C3+D3*0.5)/B3)
A4: Approval Routes | B4: =COUNTIF('Test Cases'!B:B,A4) | C4: =COUNTIFS('Test Cases'!B:B,A4,'Test Cases'!I:I,"Implemented") | D4: =COUNTIFS('Test Cases'!B:B,A4,'Test Cases'!I:I,"Partially Implemented") | E4: =B4-C4-D4 | F4: =IF(B4=0,0,(C4+D4*0.5)/B4)
A5: Approval Operations | B5: =COUNTIF('Test Cases'!B:B,A5) | C5: =COUNTIFS('Test Cases'!B:B,A5,'Test Cases'!I:I,"Implemented") | D5: =COUNTIFS('Test Cases'!B:B,A5,'Test Cases'!I:I,"Partially Implemented") | E5: =B5-C5-D5 | F5: =IF(B5=0,0,(C5+D5*0.5)/B5)
A6: Notifications | B6: =COUNTIF('Test Cases'!B:B,A6) | C6: =COUNTIFS('Test Cases'!B:B,A6,'Test Cases'!I:I,"Implemented") | D6: =COUNTIFS('Test Cases'!B:B,A6,'Test Cases'!I:I,"Partially Implemented") | E6: =B6-C6-D6 | F6: =IF(B6=0,0,(C6+D6*0.5)/B6)
A7: Search & Reference | B7: =COUNTIF('Test Cases'!B:B,A7) | C7: =COUNTIFS('Test Cases'!B:B,A7,'Test Cases'!I:I,"Implemented") | D7: =COUNTIFS('Test Cases'!B:B,A7,'Test Cases'!I:I,"Partially Implemented") | E7: =B7-C7-D7 | F7: =IF(B7=0,0,(C7+D7*0.5)/B7)
A8: Reporting | B8: =COUNTIF('Test Cases'!B:B,A8) | C8: =COUNTIFS('Test Cases'!B:B,A8,'Test Cases'!I:I,"Implemented") | D8: =COUNTIFS('Test Cases'!B:B,A8,'Test Cases'!I:I,"Partially Implemented") | E8: =B8-C8-D8 | F8: =IF(B8=0,0,(C8+D8*0.5)/B8)
A9: Permissions & Security | B9: =COUNTIF('Test Cases'!B:B,A9) | C9: =COUNTIFS('Test Cases'!B:B,A9,'Test Cases'!I:I,"Implemented") | D9: =COUNTIFS('Test Cases'!B:B,A9,'Test Cases'!I:I,"Partially Implemented") | E9: =B9-C9-D9 | F9: =IF(B9=0,0,(C9+D9*0.5)/B9)
A10: UI/UX | B10: =COUNTIF('Test Cases'!B:B,A10) | C10: =COUNTIFS('Test Cases'!B:B,A10,'Test Cases'!I:I,"Implemented") | D10: =COUNTIFS('Test Cases'!B:B,A10,'Test Cases'!I:I,"Partially Implemented") | E10: =B10-C10-D10 | F10: =IF(B10=0,0,(C10+D10*0.5)/B10)
A11: Non-Functional | B11: =COUNTIF('Test Cases'!B:B,A11) | C11: =COUNTIFS('Test Cases'!B:B,A11,'Test Cases'!I:I,"Implemented") | D11: =COUNTIFS('Test Cases'!B:B,A11,'Test Cases'!I:I,"Partially Implemented") | E11: =B11-C11-D11 | F11: =IF(B11=0,0,(C11+D11*0.5)/B11)
A12: Admin & Operations | B12: =COUNTIF('Test Cases'!B:B,A12) | C12: =COUNTIFS('Test Cases'!B:B,A12,'Test Cases'!I:I,"Implemented") | D12: =COUNTIFS('Test Cases'!B:B,A12,'Test Cases'!I:I,"Partially Implemented") | E12: =B12-C12-D12 | F12: =IF(B12=0,0,(C12+D12*0.5)/B12)
A13: Data Model | B13: =COUNTIF('Test Cases'!B:B,A13) | C13: =COUNTIFS('Test Cases'!B:B,A13,'Test Cases'!I:I,"Implemented") | D13: =COUNTIFS('Test Cases'!B:B,A13,'Test Cases'!I:I,"Partially Implemented") | E13: =B13-C13-D13 | F13: =IF(B13=0,0,(C13+D13*0.5)/B13)
A14: PDF Generation | B14: =COUNTIF('Test Cases'!B:B,A14) | C14: =COUNTIFS('Test Cases'!B:B,A14,'Test Cases'!I:I,"Implemented") | D14: =COUNTIFS('Test Cases'!B:B,A14,'Test Cases'!I:I,"Partially Implemented") | E14: =B14-C14-D14 | F14: =IF(B14=0,0,(C14+D14*0.5)/B14)
A15: TOTAL | B15: =SUM(B3:B14) | C15: =SUM(C3:C14) | D15: =SUM(D3:D14) | E15: =SUM(E3:E14) | F15: =IF(B15=0,0,(C15+D15*0.5)/B15)
A17: Actionable Test Cases — QA Test Results
A18: Category | B18: Total | C18: Passed | D18: Partial Pass | E18: Failed | F18: Blocked | G18: Pass Rate %
A19: Submission | B19: =COUNTIF('Actionable Test Cases'!B:B,A19) | C19: =COUNTIFS('Actionable Test Cases'!B:B,A19,'Actionable Test Cases'!K:K,"Passed") | D19: =COUNTIFS('Actionable Test Cases'!B:B,A19,'Actionable Test Cases'!K:K,"Partial Pass") | E19: =COUNTIFS('Actionable Test Cases'!B:B,A19,'Actionable Test Cases'!K:K,"Failed") | F19: =COUNTIFS('Actionable Test Cases'!B:B,A19,'Actionable Test Cases'!K:K,"Blocked") | G19: =IF((B19-F19)=0,0,(C19+D19*0.5)/(B19-F19))
A20: Approval | B20: =COUNTIF('Actionable Test Cases'!B:B,A20) | C20: =COUNTIFS('Actionable Test Cases'!B:B,A20,'Actionable Test Cases'!K:K,"Passed") | D20: =COUNTIFS('Actionable Test Cases'!B:B,A20,'Actionable Test Cases'!K:K,"Partial Pass") | E20: =COUNTIFS('Actionable Test Cases'!B:B,A20,'Actionable Test Cases'!K:K,"Failed") | F20: =COUNTIFS('Actionable Test Cases'!B:B,A20,'Actionable Test Cases'!K:K,"Blocked") | G20: =IF((B20-F20)=0,0,(C20+D20*0.5)/(B20-F20))
A21: AI Chat | B21: =COUNTIF('Actionable Test Cases'!B:B,A21) | C21: =COUNTIFS('Actionable Test Cases'!B:B,A21,'Actionable Test Cases'!K:K,"Passed") | D21: =COUNTIFS('Actionable Test Cases'!B:B,A21,'Actionable Test Cases'!K:K,"Partial Pass") | E21: =COUNTIFS('Actionable Test Cases'!B:B,A21,'Actionable Test Cases'!K:K,"Failed") | F21: =COUNTIFS('Actionable Test Cases'!B:B,A21,'Actionable Test Cases'!K:K,"Blocked") | G21: =IF((B21-F21)=0,0,(C21+D21*0.5)/(B21-F21))
A22: AI Retrieval | B22: =COUNTIF('Actionable Test Cases'!B:B,A22) | C22: =COUNTIFS('Actionable Test Cases'!B:B,A22,'Actionable Test Cases'!K:K,"Passed") | D22: =COUNTIFS('Actionable Test Cases'!B:B,A22,'Actionable Test Cases'!K:K,"Partial Pass") | E22: =COUNTIFS('Actionable Test Cases'!B:B,A22,'Actionable Test Cases'!K:K,"Failed") | F22: =COUNTIFS('Actionable Test Cases'!B:B,A22,'Actionable Test Cases'!K:K,"Blocked") | G22: =IF((B22-F22)=0,0,(C22+D22*0.5)/(B22-F22))
A23: Status | B23: =COUNTIF('Actionable Test Cases'!B:B,A23) | C23: =COUNTIFS('Actionable Test Cases'!B:B,A23,'Actionable Test Cases'!K:K,"Passed") | D23: =COUNTIFS('Actionable Test Cases'!B:B,A23,'Actionable Test Cases'!K:K,"Partial Pass") | E23: =COUNTIFS('Actionable Test Cases'!B:B,A23,'Actionable Test Cases'!K:K,"Failed") | F23: =COUNTIFS('Actionable Test Cases'!B:B,A23,'Actionable Test Cases'!K:K,"Blocked") | G23: =IF((B23-F23)=0,0,(C23+D23*0.5)/(B23-F23))
A24: User Role | B24: =COUNTIF('Actionable Test Cases'!B:B,A24) | C24: =COUNTIFS('Actionable Test Cases'!B:B,A24,'Actionable Test Cases'!K:K,"Passed") | D24: =COUNTIFS('Actionable Test Cases'!B:B,A24,'Actionable Test Cases'!K:K,"Partial Pass") | E24: =COUNTIFS('Actionable Test Cases'!B:B,A24,'Actionable Test Cases'!K:K,"Failed") | F24: =COUNTIFS('Actionable Test Cases'!B:B,A24,'Actionable Test Cases'!K:K,"Blocked") | G24: =IF((B24-F24)=0,0,(C24+D24*0.5)/(B24-F24))
A25: TOTAL | B25: =SUM(B19:B24) | C25: =SUM(C19:C24) | D25: =SUM(D19:D24) | E25: =SUM(E19:E24) | F25: =SUM(F19:F24) | G25: =IF((B25-F25)=0,0,(C25+D25*0.5)/(B25-F25))
A27: Legend
A28: Test Cases Status:
A29: Implemented = feature fully built and working | Partially Implemented = some functionality exists but gaps remain | Not Yet Implemented = not started
A30: Coverage % = (Implemented + Partially Implemented × 0.5) / Total
A32: Actionable Test Cases Status:
A33: Passed = test passed | Partial Pass = partially working | Failed = test failed | Blocked = cannot test (dependency/prerequisite missing)
A34: Pass Rate % = (Passed + Partial Pass × 0.5) / (Total − Blocked)
A37: Actionable Test Bugs — Bug Summary
A38: Category | B38: Total | C38: Critical | D38: Major | E38: Minor | F38: Bug | G38: Enhancement
A39: Submission | B39: =COUNTIF('Actionable Test Bugs'!C:C,A39) | C39: =COUNTIFS('Actionable Test Bugs'!C:C,A39,'Actionable Test Bugs'!G:G,"Critical") | D39: =COUNTIFS('Actionable Test Bugs'!C:C,A39,'Actionable Test Bugs'!G:G,"Major") | E39: =COUNTIFS('Actionable Test Bugs'!C:C,A39,'Actionable Test Bugs'!G:G,"Minor") | F39: =COUNTIFS('Actionable Test Bugs'!C:C,A39,'Actionable Test Bugs'!F:F,"Bug") | G39: =COUNTIFS('Actionable Test Bugs'!C:C,A39,'Actionable Test Bugs'!F:F,"Enhancement")
A40: Approval | B40: =COUNTIF('Actionable Test Bugs'!C:C,A40) | C40: =COUNTIFS('Actionable Test Bugs'!C:C,A40,'Actionable Test Bugs'!G:G,"Critical") | D40: =COUNTIFS('Actionable Test Bugs'!C:C,A40,'Actionable Test Bugs'!G:G,"Major") | E40: =COUNTIFS('Actionable Test Bugs'!C:C,A40,'Actionable Test Bugs'!G:G,"Minor") | F40: =COUNTIFS('Actionable Test Bugs'!C:C,A40,'Actionable Test Bugs'!F:F,"Bug") | G40: =COUNTIFS('Actionable Test Bugs'!C:C,A40,'Actionable Test Bugs'!F:F,"Enhancement")
A41: AI Chat | B41: =COUNTIF('Actionable Test Bugs'!C:C,A41) | C41: =COUNTIFS('Actionable Test Bugs'!C:C,A41,'Actionable Test Bugs'!G:G,"Critical") | D41: =COUNTIFS('Actionable Test Bugs'!C:C,A41,'Actionable Test Bugs'!G:G,"Major") | E41: =COUNTIFS('Actionable Test Bugs'!C:C,A41,'Actionable Test Bugs'!G:G,"Minor") | F41: =COUNTIFS('Actionable Test Bugs'!C:C,A41,'Actionable Test Bugs'!F:F,"Bug") | G41: =COUNTIFS('Actionable Test Bugs'!C:C,A41,'Actionable Test Bugs'!F:F,"Enhancement")
A42: AI Retrieval | B42: =COUNTIF('Actionable Test Bugs'!C:C,A42) | C42: =COUNTIFS('Actionable Test Bugs'!C:C,A42,'Actionable Test Bugs'!G:G,"Critical") | D42: =COUNTIFS('Actionable Test Bugs'!C:C,A42,'Actionable Test Bugs'!G:G,"Major") | E42: =COUNTIFS('Actionable Test Bugs'!C:C,A42,'Actionable Test Bugs'!G:G,"Minor") | F42: =COUNTIFS('Actionable Test Bugs'!C:C,A42,'Actionable Test Bugs'!F:F,"Bug") | G42: =COUNTIFS('Actionable Test Bugs'!C:C,A42,'Actionable Test Bugs'!F:F,"Enhancement")
A43: Status | B43: =COUNTIF('Actionable Test Bugs'!C:C,A43) | C43: =COUNTIFS('Actionable Test Bugs'!C:C,A43,'Actionable Test Bugs'!G:G,"Critical") | D43: =COUNTIFS('Actionable Test Bugs'!C:C,A43,'Actionable Test Bugs'!G:G,"Major") | E43: =COUNTIFS('Actionable Test Bugs'!C:C,A43,'Actionable Test Bugs'!G:G,"Minor") | F43: =COUNTIFS('Actionable Test Bugs'!C:C,A43,'Actionable Test Bugs'!F:F,"Bug") | G43: =COUNTIFS('Actionable Test Bugs'!C:C,A43,'Actionable Test Bugs'!F:F,"Enhancement")
A44: User Role | B44: =COUNTIF('Actionable Test Bugs'!C:C,A44) | C44: =COUNTIFS('Actionable Test Bugs'!C:C,A44,'Actionable Test Bugs'!G:G,"Critical") | D44: =COUNTIFS('Actionable Test Bugs'!C:C,A44,'Actionable Test Bugs'!G:G,"Major") | E44: =COUNTIFS('Actionable Test Bugs'!C:C,A44,'Actionable Test Bugs'!G:G,"Minor") | F44: =COUNTIFS('Actionable Test Bugs'!C:C,A44,'Actionable Test Bugs'!F:F,"Bug") | G44: =COUNTIFS('Actionable Test Bugs'!C:C,A44,'Actionable Test Bugs'!F:F,"Enhancement")
A45: TOTAL | B45: =SUM(B39:B44) | C45: =SUM(C39:C44) | D45: =SUM(D39:D44) | E45: =SUM(E39:E44) | F45: =SUM(F39:F44) | G45: =SUM(G39:G44)

Sheet Actionable Test Cases
A1: TC-ID | B1: Category | C1: Feature | D1: Test Case Title | E1: Type | F1: Preconditions | G1: Test Steps | H1: Expected Result | I1: Test Files | J1: Priority | K1: Pass Status | L1: Link | M1: Notes | N1: Spec Ref
A2: KT-SUB-001 | B2: Submission | C2: Submit with valid EN doc | D2: Submit ringi with valid English document attachment | E2: Main | F2: Login as staff@gmail.com | G2: 1. Login staff@gmail.com at https://eb-filemg-development.vercel.app 2. Click 'New Submission' → Category: Purchasing 3. Title: 'Annual Software License Renewal', Priority: High, Dept: Sales 4. Add Item: 'Adobe CC Enterprise License' ×1, $12,500 5. Vendor: 'Adobe Inc.', Payment: 2026-03-15, Bank Transfer 6. Required by: 2026-03-01 09:00 7. Reason: 'Annual renewal of Adobe CC licenses, expires March 31' 8. Purpose: 'Maintain design tool access for Sales marketing' 9. Attach ringi_en_detailed_license_renewal.docx 10. Verify Approval Route → Click 'Create Submission' | H2: Submission created with 'Pending' status. Title='Annual Software License Renewal', Priority=High, Amount=$12,500. File attached and visible in detail view. Approval route displayed. | I2: ringi_en_detailed_license_renewal.docx | J2: P1 | K2: Passed | L2: https://jam.dev/c/c59ad198-fb75-4953-8e4c-279d811bdcc1 | M2: there is subtle bug: Submitted By Staff null --- It would be beneficial if there is Draft submission status as well | N2: Spec 6.1 (Submission) → "Form fields: Subject, Category (Purchasing, Contracts, Expenses, Misc.), Amount (tax incl./excl.), Tax category, Payment terms, Vendor/Counterparty, Purpose, Period, Budget code, Project, Desired approval date, Applicant/Department."
A3: KT-SUB-002 | B3: Submission | C3: Submit with valid JP doc | D3: Submit ringi with valid Japanese document attachment | E3: Main | F3: Login as staff@gmail.com | G3: 1. Login staff@gmail.com 2. New Submission → Category: Purchasing 3. Title: 'オフィスチェア購入稟議', Priority: Medium, Dept: 総務部 4. Add Item: 'エルゴノミクスオフィスチェア' ×10, ¥50,000 5. Enable Tax: ON, Rate: 10% 6. Vendor: 'オフィス家具株式会社', Payment: 2026-04-01, Bank Transfer 7. Required by: 2026-03-20 10:00 8. Reason: '総務部用オフィスチェア10脚の購入申請' 9. Purpose: '従業員の作業環境改善' 10. Attach ringi_jp_purchase_chairs.docx → Create Submission | H3: Submission created with JP content, no garbled text. Status 'Pending'. Tax: ¥500,000 + 10% = ¥550,000. File attached. | I3: ringi_jp_purchase_chairs.docx | J3: P1 | K3: Passed | L3: https://jam.dev/c/e7c5d836-7e67-4e76-82d7-9d8f3957ce0d | M3: there is subtle bug regarding the tax number in form and also in details | N3: Spec 6.1 (Submission) → "Form fields: Subject, Category (Purchasing, Contracts, Expenses, Misc.), Amount (tax incl./excl.), Tax category, Payment terms, Vendor/Counterparty, Purpose, Period, Budget code, Project, Desired approval date, Applicant/Department."
A4: KT-SUB-003 | B4: Submission | C4: Submit with all fields + line items | D4: Submit with all fields filled and multiple line items | E4: Main | F4: Login as staff@gmail.com | G4: 1. Login staff@gmail.com 2. New Submission → Category: Purchasing 3. Title: 'Dell 4K Monitor Purchase for Development Team', Priority: Medium, Dept: IT 4. Add Item 1: 'Dell UltraSharp U2723QE 27"' ×5, $750 5. Add Item 2: 'Monitor Stand Arm' ×5, $0 6. Vendor: 'Dell Technologies', Payment: 2026-04-15, Credit Card 7. Required by: 2026-04-01 14:00 8. Reason: 'Purchase 5x 4K monitors for dev team' 9. Purpose: 'Improve developer productivity with high-res displays' 10. Remarks: 'Deliver to Building A, Floor 3' 11. Attach ringi_en_purchase_monitors.docx → Create Submission | H4: All fields saved. Both line items visible (monitors + stands). Amount=$3,750. Attachment visible and downloadable. Status 'Pending'. | I4: ringi_en_purchase_monitors.docx | J4: P1 | K4: Passed | L4: https://jam.dev/c/e5777a3f-6626-4419-92d8-8884a9ef544d | M4: there is bug in detail when clicked the filed it show xml file | N4: Spec 6.1 (Submission) → "Form fields: Subject, Category (Purchasing, Contracts, Expenses, Misc.), Amount (tax incl./excl.), Tax category, Payment terms, Vendor/Counterparty, Purpose, Period, Budget code, Project, Desired approval date, Applicant/Department."
A5: KT-SUB-004 | B5: Submission | C5: Submit minimum fields | D5: Submit with minimum required fields only | E5: Basic | F5: Login as staff@gmail.com | G5: 1. Login staff@gmail.com 2. New Submission → Category: Other 3. Title: 'Minimum Fields Test', Priority: Low, Dept: General 4. No items, no attachment, no remarks 5. Vendor: 'N/A', Payment: 2026-05-01, Cash 6. Required by: 2026-04-30 17:00 7. Reason: 'Testing minimum required fields' 8. Purpose: 'QA Test' 9. Click 'Create Submission' | H5: Submission created with only required data. No validation errors on optional fields. Status 'Pending' on dashboard. | I5: (none) | J5: P2 | K5: Passed | L5: https://jam.dev/c/ca785d03-1021-4e40-987f-54b86a4660ea | N5: Spec 6.1 (Submission) → "Form fields: Subject, Category (Purchasing, Contracts, Expenses, Misc.), Amount (tax incl./excl.), Tax category, Payment terms, Vendor/Counterparty, Purpose, Period, Budget code, Project, Desired approval date, Applicant/Department."
A6: KT-SUB-005 | B6: Submission | C6: Submit with Excel attachment | D6: Submit with Excel spreadsheet ringi attachment | E6: Basic | F6: Login as staff@gmail.com | G6: 1. Login staff@gmail.com 2. New Submission → Category: Expense 3. Title: '会計ソフト更新', Priority: Medium, Dept: 経理部 4. Add Item: 'freee会計 年間ライセンス' ×1, ¥600,000 5. Vendor: 'freee株式会社', Payment: 2026-04-01, Bank Transfer 6. Required by: 2026-03-25 10:00 7. Reason: '経理部の会計ソフトfreeeの年間ライセンス更新' 8. Purpose: '経理業務の継続' 9. Attach ringi_jp_spreadsheet_accounting.xlsx → Create Submission | H6: Excel file (.xlsx) accepted as attachment. Submission created. File downloadable from detail view. | I6: ringi_jp_spreadsheet_accounting.xlsx | J6: P2 | K6: Passed | L6: https://jam.dev/c/5a4cb745-883b-45d7-9be7-dfc259942d1f | N6: Spec 6.1 (Submission) → "Attachments: Quotes, contracts, and related materials. No tampering allowed after approval (must re-apply as a new version)."
A7: KT-SUB-006 | B7: Submission | C7: Edit pending submission | D7: Edit an existing pending submission | E7: Basic | F7: Existing pending submission by staff@gmail.com | G7: 1. Login staff@gmail.com 2. Go to dashboard, click pending submission card → detail /approval-requests/[id] 3. Click Edit 4. Change title to 'Updated: [original title]' 5. Change Priority to Critical 6. Save changes | H7: Edit form loads with pre-filled data. Changes saved. Submission remains 'Pending'. Updated values visible in detail. | I7: (none) | J7: P2 | K7: Passed | L7: https://jam.dev/c/d10f06f9-6592-48b7-bdd6-b8f727a38b55 | N7: Spec 6.1 (Submission) → "Statuses: Draft / Applying / Waiting for Approval (by stage) / Sent Back / Rejected / Approved / Expired."
A8: KT-SUB-007 | B8: Submission | C8: Submit with image file | D8: Submit with beach image as attachment (wrong file type) | E8: Edge Case | F8: Login as staff@gmail.com | G8: 1. Login staff@gmail.com 2. New Submission → Category: Other 3. Title: 'Edge Case Test - Image Upload', Priority: Low, Dept: QA 4. Vendor: 'Test', Payment: 2026-05-01, Cash 5. Required by: 2026-04-30 17:00 6. Reason: 'Testing image file upload behavior', Purpose: 'QA Edge Case' 7. Attach edge_beach_image.jpg 8. Attempt to submit | H8: System either rejects image file type with clear message, or accepts gracefully (no crash, no corrupt data). | I8: edge_beach_image.jpg | J8: P2 | K8: Passed | L8: https://jam.dev/c/9809373a-1afa-4a8d-8540-e4836b18b2c5 | N8: Spec 6.1 (Submission) → "Attachments: Quotes, contracts, and related materials. No tampering allowed after approval (must re-apply as a new version)."
A9: KT-SUB-008 | B9: Submission | C9: Submit with empty PDF | D9: Submit with empty/blank PDF attachment | E9: Edge Case | F9: Login as staff@gmail.com | G9: 1. Login staff@gmail.com 2. New Submission → Category: Other 3. Title: 'Edge Case Test - Empty PDF', Priority: Low, Dept: QA 4. Vendor: 'Test', Payment: 2026-05-01, Cash 5. Required by: 2026-04-30 17:00 6. Reason: 'Testing empty PDF upload behavior', Purpose: 'QA Edge Case' 7. Attach edge_empty_file.pdf (blank PDF) 8. Click 'Create Submission' | H9: System handles blank PDF without crashing. Either accepts or shows appropriate warning. | I9: edge_empty_file.pdf | J9: P3 | K9: Passed | L9: https://jam.dev/c/22a8a004-c862-44b8-9dbf-5c70b1825501 | N9: Spec 6.1 (Submission) → "Attachments: Quotes, contracts, and related materials. No tampering allowed after approval (must re-apply as a new version)."
A10: KT-SUB-009 | B10: Submission | C10: Submit with special chars filename | D10: Submit with Japanese characters in filename | E10: Edge Case | F10: Login as staff@gmail.com | G10: 1. Login staff@gmail.com 2. New Submission → Category: Other 3. Title: 'Edge Case Test - Special Characters', Priority: Low, Dept: QA 4. Vendor: 'Test', Payment: 2026-05-01, Cash 5. Required by: 2026-04-30 17:00 6. Reason: 'Testing special character filename handling', Purpose: 'QA Edge Case' 7. Attach edge_special_chars_名前.docx (JP chars in filename) 8. Click 'Create Submission' | H10: File uploaded. Japanese characters in filename preserved and displayed correctly. Submission created without errors. | I10: edge_special_chars_名前.docx | J10: P2 | K10: Failed | L10: https://jam.dev/c/e9e24876-69bd-4c41-ba8b-0886be4cd867 | M10: error file char name | N10: Spec 6.1 (Submission) → "Attachments: Quotes, contracts, and related materials. No tampering allowed after approval (must re-apply as a new version)."
A11: KT-SUB-010 | B11: Submission | C11: Submit with very large amount | D11: Submit with extremely large amount value | E11: Edge Case | F11: Login as staff@gmail.com | G11: 1. Login staff@gmail.com 2. New Submission → Category: Other 3. Title: 'Edge Case Test - Large Amount', Priority: Low, Dept: QA 4. Add Item: 'Large Amount Test Item' ×1, $999,999,999,999 5. Vendor: 'Test', Payment: 2026-05-01, Cash 6. Required by: 2026-04-30 17:00 7. Reason: 'Testing large amount handling', Purpose: 'QA Edge Case' 8. Click 'Create Submission' | H11: System either accepts the large number or shows validation for max amount. No crash or data corruption. | I11: (none) | J11: P3 | K11: Failed | L11: https://jam.dev/c/e7cb4064-6b39-4b65-a1e8-e609eef7f6e5 | M11: number overflow | N11: Spec 6.1 (Submission) → "Form fields: Subject, Category (Purchasing, Contracts, Expenses, Misc.), Amount (tax incl./excl.), Tax category, Payment terms, Vendor/Counterparty, Purpose, Period, Budget code, Project, Desired approval date, Applicant/Department."
A12: KT-APR-001 | B12: Approval | C12: Manager approves ringi | D12: Manager approves a pending ringi submission | E12: Main | F12: Pending submission exists (submitted by staff) | G12: 1. Login manager@gmail.com at https://eb-filemg-development.vercel.app 2. Find pending ringi card on dashboard 3. Click card → detail /approval-requests/[id] 4. Review Details tab, then Files tab 5. Click green Approve button 6. (Optional) Notes: 'Approved - budget within Q1 allocation' 7. Click Confirm 8. Switch to staff@gmail.com → verify 'Approved' on dashboard | H12: Status changes to 'Approved'. Recorded with timestamp in Timeline tab. Green CheckCircle icon. Staff sees 'Approved'. | I12: (none) | J12: P1 | K12: Failed | L12: https://jam.dev/c/432754ce-879c-4937-a5a1-f315125385af | M12: There is glitch of approval with status and then it is empty (but there is workaround to login as staff first and then logout and then login as manager) | N12: Spec 6.3 (Approval Operations) → "Statuses: Draft / Applying / Waiting for Approval (by stage) / Sent Back / Rejected / Approved / Expired."
A13: KT-APR-002 | B13: Approval | C13: Manager rejects with reason | D13: Manager rejects ringi with rejection reason | E13: Main | F13: Pending submission exists | G13: 1. Login manager@gmail.com 2. Find pending ringi → detail /approval-requests/[id] 3. Click red Reject button 4. Try submitting without reason → verify validation error 5. Enter: 'Budget exceeded for Q1. Please reduce or defer to Q2.' 6. Click Confirm | H13: Validation error when no reason. Status → 'Rejected' with XCircle icon. Reason in Timeline tab. Staff sees rejection reason. | I13: (none) | J13: P1 | K13: Blocked | L13: blocked of the KT-APR-001 | N13: Spec 6.3 (Approval Operations) → "Reason comments are mandatory for send-backs and rejections. Difference notes for re-applications."
A14: KT-APR-003 | B14: Approval | C14: Manager requests revision | D14: Manager sends back ringi for revision | E14: Basic | F14: Pending submission exists | G14: 1. Login manager@gmail.com 2. Open pending ringi detail /approval-requests/[id] 3. Click 'Request Revision' / 'Send Back' 4. Enter: 'Please add detailed cost breakdown and attach vendor quotation.' 5. Click Confirm | H14: Status → 'Need Revision'. Feedback saved in Timeline tab. Staff sees feedback and edit option. | I14: (none) | J14: P2 | K14: Blocked | L14: blocked of the KT-APR-001 | N14: Spec 6.3 (Approval Operations) → "Reason comments are mandatory for send-backs and rejections. Difference notes for re-applications."
A15: KT-APR-004 | B15: Approval | C15: Staff re-edits after revision | D15: Staff edits and resubmits after revision request | E15: Basic | F15: Submission with "Need Revision" status | G15: 1. Login staff@gmail.com 2. Find 'Need Revision' submission on dashboard 3. Open detail /approval-requests/[id] → Click Edit 4. Update Reason with cost breakdown, adjust amount/items 5. Click Re-submit / Save | H15: Edit form loads with pre-filled data. Changes saved. Status returns to 'Pending' for manager re-review. | I15: (none) | J15: P2 | K15: Blocked | L15: blocked of the KT-APR-001 | N15: Spec 6.3 (Approval Operations) → "Reason comments are mandatory for send-backs and rejections. Difference notes for re-applications."
A16: KT-APR-005 | B16: Approval | C16: Staff blocked from approving | D16: Staff tries to approve a submission (should be blocked) | E16: Edge Case | F16: Pending submission exists | G16: 1. Login staff@gmail.com 2. Open pending submission detail /approval-requests/[id] 3. Inspect ALL action buttons on the page | H16: No Approve, Reject, or Request Revision buttons visible. Staff can only view details, files, and timeline. | I16: (none) | J16: P1 | K16: Passed | L16: https://jam.dev/c/ee692561-c9db-4fc1-9f6c-a9befb6953f0 | N16: Spec 6.7 (Permissions & Security) → "RBAC: Initiators edit/view their own applications, approvers operate on assigned cases, admins view all and change settings."
A17: KT-APR-006 | B17: Approval | C17: Double-approve attempt | D17: Attempt to approve an already-approved ringi | E17: Edge Case | F17: Already approved submission | G17: 1. Login manager@gmail.com 2. Open already-approved submission /approval-requests/[id] 3. Check if Approve/Reject buttons are still available | H17: Approve/Reject buttons NOT available for already-approved submissions. 'Approved' with green CheckCircle. No further actions. | I17: (none) | J17: P3 | K17: Blocked | N17: Spec 6.3 (Approval Operations) → "Statuses: Draft / Applying / Waiting for Approval (by stage) / Sent Back / Rejected / Approved / Expired."
A18: KT-APR-007 | B18: Approval | C18: Manager self-approval | D18: Manager tries to approve own submission | E18: Edge Case | F18: Manager has submitted own ringi | G18: 1. Login manager@gmail.com 2. New Submission → Category: Other 3. Title: 'Manager Self-Approval Test', Priority: Low, Dept: Management 4. Vendor: 'Internal', Payment: 2026-05-01, Cash 5. Required by: 2026-04-30 17:00 6. Reason: 'Testing self-approval behavior', Purpose: 'QA Test' 7. After submission, open own submission detail 8. Try to approve own submission | H18: Document actual behavior: self-approval allowed or blocked? If blocked: clear error. If allowed: processes normally. | I18: (none) | J18: P2 | K18: Passed | L18: https://jam.dev/c/af2dced4-d706-4673-ac8d-6723520dce0f | M18: Clarify the Requirement | N18: Spec 6.3 (Approval Operations) → "RBAC: Initiators edit/view their own applications, approvers operate on assigned cases, admins view all and change settings."
A19: KT-APR-008 | B19: Approval | C19: Quick-approve from dashboard | D19: Manager uses quick-approve action from card | E19: Basic | F19: Pending submissions visible on dashboard | G19: 1. Login manager@gmail.com 2. Go to dashboard 3. Find pending ringi card 4. Look for quick-approve action on card itself 5. If available, use quick-approve without opening detail | H19: Quick-approve action available on cards (if implemented). Approval succeeds from dashboard. Status updates immediately. | I19: (none) | J19: P2 | K19: Passed | N19: Spec 6.4 (Chat Integration), Spec 9 (UI/UX) → "Approve/send back from chat cards."
A20: KT-AIC-001 | B20: AI Chat | C20: Create ringi via AI (EN) | D20: Ask AI to create ringi from natural language in English | E20: Main | F20: Login as staff@gmail.com | G20: 1. Login staff@gmail.com 2. Go to https://eb-filemg-development.vercel.app/ (new chat) 3. Type: "Create a ringi for purchasing 10 office laptops, total cost $15,000" 4. Send and wait for AI response | H20: AI generates ringi draft with title, description, amount ($15,000). Response in English. Chat thread created (/c/[threadId]). | I20: (none) | J20: P1 | K20: Partial Pass | L20: https://jam.dev/c/3ff23937-7197-4d13-9381-65ef837e3113 | M20: AI generate pending, but not Draft it lead to user cannot edit the ringi when use try to edit the ringi, it got bugs | N20: Spec 5 (Business Flow), Spec 6.1, Spec 6.4 → "Initiator opens the Ringi initiation form via chat, enters required items and attachments, and submits."
A21: KT-AIC-002 | B21: AI Chat | C21: Create ringi via AI (JP) | D21: Ask AI to create ringi from natural language in Japanese | E21: Main | F21: Login as staff@gmail.com | G21: 1. Login staff@gmail.com 2. Go to new chat at / 3. Type: "ノートPC10台購入の稟議書を作成してください。合計金額150万円" 4. Send and wait for AI response | H21: AI generates ringi draft in Japanese with appropriate title and amount (¥1,500,000 / 150万円). | I21: (none) | J21: P1 | K21: Partial Pass | L21: https://jam.dev/c/37d7d204-3527-4e40-aad0-e51fab33d42a | M21: AI generate pending, but not Draft it lead to user cannot edit the ringi it got asking again and again same things | N21: Spec 5 (Business Flow), Spec 6.1, Spec 6.4 → "Initiator opens the Ringi initiation form via chat, enters required items and attachments, and submits."
A22: KT-AIC-003 | B22: AI Chat | C22: Upload doc + AI summarize | D22: Upload ringi doc and ask AI to summarize | E22: Basic | F22: Login as staff@gmail.com | G22: 1. Login staff@gmail.com 2. Go to new chat at / 3. Click paperclip → select ringi_en_detailed_license_renewal.docx 4. Verify file appears as attachment preview 5. Type: "Please summarize this ringi document" 6. Send and wait for response | H22: AI processes document. Summary mentions Adobe CC / license renewal, $12,500, Sales dept or Hanako Suzuki. Accurate to content. | I22: ringi_en_detailed_license_renewal.docx | J22: P1 | K22: Passed | L22: https://jam.dev/c/d1706ed5-abf0-4a53-b19d-a1368e703521 | N22: Spec 6.1, Spec 6.4 (Chat Integration) → "Contextual input assistance: Summarize chat messages to suggest initial form values."
A23: KT-AIC-004 | B23: AI Chat | C23: Ask about doc in Japanese | D23: Ask AI about uploaded document in Japanese | E23: Basic | F23: Login as staff@gmail.com | G23: 1. Login staff@gmail.com 2. Go to new chat at / 3. Click paperclip → select ringi_jp_standard_salesforce.docx 4. Type: "この稟議書の内容を教えてください" 5. Send and review response | H23: AI responds in Japanese. Summary mentions Salesforce / 営業支援ツール, ¥4,100,000, 営業部 or 鈴木花子. | I23: ringi_jp_standard_salesforce.docx | J23: P2 | K23: Passed | L23: https://jam.dev/c/40723d7b-aae3-47e5-81e3-d83304091945 | M23: there is UI glitch, also the loader is not appeared | N23: Spec 6.1, Spec 6.4 (Chat Integration) → "Contextual input assistance: Summarize chat messages to suggest initial form values."
A24: KT-AIC-005 | B24: AI Chat | C24: Upload image for ringi | D24: Upload beach image and ask AI to create ringi from it | E24: Edge Case | F24: Login as staff@gmail.com | G24: 1. Login staff@gmail.com 2. Go to new chat at / 3. Click paperclip → select edge_beach_image.jpg (beach photo) 4. Type: "Create a ringi from this document" 5. Send and review response | H24: AI does not crash. Indicates file is not a valid ringi document or cannot extract info from image. Graceful response. | I24: edge_beach_image.jpg | J24: P2 | K24: Passed | L24: https://jam.dev/c/f573209c-c362-421e-8cb7-e5367245fd4a | N24: Spec 6.1, Spec 6.4 (Chat Integration) → "Attachments: Quotes, contracts, and related materials. No tampering allowed after approval (must re-apply as a new version)."
A25: KT-AIC-006 | B25: AI Chat | C25: Gibberish/unrelated question | D25: Ask AI gibberish or unrelated question | E25: Edge Case | F25: Login as staff@gmail.com | G25: 1. Login staff@gmail.com 2. Go to new chat at / 3. Type: "asdfghjkl what is the weather today?" 4. Send and review response | H25: AI responds without crashing. Redirects to ringi-related help or provides polite response about scope. | I25: (none) | J25: P3 | K25: Passed | L25: https://jam.dev/c/aea773c3-1e12-4378-9647-a6ae532b19d8 | N25: Spec 6.4 (Chat Integration) → "Contextual input assistance: Summarize chat messages to suggest initial form values."
A26: KT-AIC-007 | B26: AI Chat | C26: Non-ringi doc for submission | D26: Upload non-ringi document and ask to create submission | E26: Edge Case | F26: Login as staff@gmail.com | G26: 1. Login staff@gmail.com 2. Go to new chat at / 3. Click paperclip → select edge_large_file.pdf (non-ringi content) 4. Type: "Create a ringi submission from this" 5. Send and review response | H26: AI processes document. Either extracts whatever info possible or indicates no ringi data. Graceful response. | I26: edge_large_file.pdf | J26: P2 | K26: Passed | L26: https://jam.dev/c/fa7689ce-95ec-4753-9c3c-7150f4b6a62a | N26: Spec 6.1, Spec 6.4 (Chat Integration) → "Contextual input assistance: Summarize chat messages to suggest initial form values."
A27: KT-AIC-008 | B27: AI Chat | C27: Multi-turn conversation | D27: Multi-turn conversation to build ringi incrementally | E27: Basic | F27: Login as staff@gmail.com | G27: 1. Login staff@gmail.com 2. Go to new chat at / 3. Msg 1: "I need to create a ringi for purchasing new office furniture" 4. Wait for response 5. Msg 2: "The budget is $8,000 for 10 standing desks from IKEA" 6. Wait for response 7. Msg 3: "Please finalize with department 'Operations' and requestor 'John Smith'" 8. Review final output | H27: AI maintains context across 3 turns. Final ringi: furniture, $8,000, 10 standing desks, IKEA, Operations, John Smith. Same thread URL. | I27: (none) | J27: P2 | K27: Partial Pass | L27: https://jam.dev/c/3517856c-1367-41bc-af8b-43a0a096d508 | M27: should comply with minimum required fields | N27: Spec 5 (Business Flow), Spec 6.4 → "Initiator opens the Ringi initiation form via chat, enters required items and attachments, and submits."
A28: KT-AIR-001 | B28: AI Retrieval | C28: Ask submission status (EN) | D28: Ask AI for status of specific submission in English | E28: Main | F28: Staff has existing submissions | G28: 1. Login staff@gmail.com (has existing submissions) 2. Note title of existing submission (e.g., 'Annual Software License Renewal') 3. Go to new chat at / 4. Type: "What is the status of 'Annual Software License Renewal'?" 5. Send and review response | H28: AI retrieves correct submission. Reports current status (Pending/Approved/etc.). Info matches dashboard. SearchResultsCard may display. | I28: (none) | J28: P1 | K28: Partial Pass | L28: https://jam.dev/c/6dfb78f5-bb0d-4d70-a03a-929b74ae0e49 | M28: it show the correct summary, yet files shown pending submssion are too manies | N28: Spec 6.5 (Search & Reference) → "Search/filter by Ringi ID, subject, applicant, department, amount range, status, and period."
A29: KT-AIR-002 | B29: AI Retrieval | C29: Find document by name | D29: Ask AI to find/retrieve a specific document by name | E29: Main | F29: Documents exist in system | G29: 1. Login staff@gmail.com 2. Go to new chat at / 3. Type: "Find the document called 'Dell 4K Monitor Purchase for Development Team'" 4. Send and review response | H29: AI locates submission. Provides status, date, amount info. SearchResultsCard with file card(s) and Open/Share buttons. | I29: (none) | J29: P1 | K29: Failed | L29: https://jam.dev/c/07e3abd6-675a-4cbd-b172-39321f9f55ec | M29: search about monitor yet not shown | N29: Spec 6.5 (Search & Reference) → "Search/filter by Ringi ID, subject, applicant, department, amount range, status, and period."
A30: KT-AIR-003 | B30: AI Retrieval | C30: Review submission status | D30: Ask AI to review and check submission status | E30: Basic | F30: Staff has submissions | G30: 1. Login staff@gmail.com (has multiple submissions) 2. Go to new chat at / 3. Type: "Review and check my submission status" 4. Send and review response | H30: AI lists staff's submissions with current statuses. List matches dashboard at /. | I30: (none) | J30: P2 | K30: Passed | L30: https://jam.dev/c/d1931bae-8fb2-47b1-81f8-e6b126a3675b | M30: but should be have pagination like to avoid long time, if many files also the numbering shown always 1 (which is bug) | N30: Spec 6.5 (Search & Reference) → "Search/filter by Ringi ID, subject, applicant, department, amount range, status, and period."
A31: KT-AIR-004 | B31: AI Retrieval | C31: Search in Japanese | D31: Search for document/status in Japanese | E31: Basic | F31: JP documents exist | G31: 1. Login staff@gmail.com (JP submissions exist) 2. Go to new chat at / 3. Type: "稟議書の状態を確認してください" 4. Send and review response | H31: AI responds in Japanese. Lists submissions with statuses. Japanese titles displayed correctly. | I31: (none) | J31: P2 | K31: Passed | L31: https://jam.dev/c/c2455701-1403-4615-9574-15a0ea25ec9c | M31: pass yet buggy, 1st submit waiting so long, the sent message is not disabled thus can prompt 2 times, and the response appear two times | N31: Spec 6.5 (Search & Reference) → "Search/filter by Ringi ID, subject, applicant, department, amount range, status, and period."
A32: KT-AIR-005 | B32: AI Retrieval | C32: Non-existent document | D32: Ask for non-existent document/submission | E32: Edge Case | F32: Login as staff@gmail.com | G32: 1. Login staff@gmail.com 2. Go to new chat at / 3. Type: "What is the status of ringi XYZ-NONEXISTENT-999?" 4. Send and review response | H32: AI does NOT return fabricated data. Indicates no matching submission found. Suggests checking title or listing existing. | I32: (none) | J32: P2 | K32: Passed | L32: https://jam.dev/c/b6fabc61-818c-473a-b6b5-d1a8bd6b611a | M32: Pass yet buggy, it give all pending requests | N32: Spec 6.5 (Search & Reference) → "Search/filter by Ringi ID, subject, applicant, department, amount range, status, and period."
A33: KT-AIR-006 | B33: AI Retrieval | C33: Another user's submission | D33: Ask for another user's submission status | E33: Edge Case | F33: Multiple users have submissions | G33: 1. Login staff@gmail.com 2. Go to new chat at / 3. Type: "What is the status of 'Manager Self-Approval Test'?" (manager's submission) 4. Send and review response | H33: AI respects data boundaries. Either denies access, shows limited info, or indicates another user's submission. | I33: (none) | J33: P2 | K33: Partial Pass | L33: https://jam.dev/c/af3d194a-5853-473f-87f7-df2e469fe7c3 | M33: It did not show yet the AI hallucinate | N33: Spec 6.5, Spec 6.7 (Permissions) → "RBAC: Initiators edit/view their own applications, approvers operate on assigned cases, admins view all and change settings."
A34: KT-STS-001 | B34: Status | C34: Pending status display | D34: Verify pending status display on card and detail | E34: Main | F34: Fresh submission just created | G34: 1. Login staff@gmail.com 2. New Submission → Category: Other 3. Title: 'Status Test - Pending', Priority: Low, Dept: QA 4. Vendor: 'Test', Payment: 2026-05-01, Cash 5. Required by: 2026-04-30 17:00 6. Reason: 'Testing pending status display', Purpose: 'QA Status Test' 7. After submission, find card on dashboard 8. Click card → detail view | H34: 'Pending' badge with orange styling on dashboard card and detail view. Submission in active list. | I34: (none) | J34: P1 | K34: Passed | L34: same as previous | N34: Spec 6.3, Spec 9 (UI/UX) → "Statuses: Draft / Applying / Waiting for Approval (by stage) / Sent Back / Rejected / Approved / Expired."
A35: KT-STS-002 | B35: Status | C35: Approved status display | D35: Verify approved status after manager approval | E35: Main | F35: Manager approves a submission | G35: 1. Login manager@gmail.com 2. Find 'Status Test - Pending' card → detail /approval-requests/[id] 3. Click green Approve → Confirm 4. Switch to staff@gmail.com 5. Find now-approved card on dashboard 6. Click → detail view | H35: 'Approved' badge with green color and CheckCircle icon on card and detail. Approval info in Timeline tab. | I35: (none) | J35: P1 | K35: Passed | N35: Spec 6.3, Spec 9 (UI/UX) → "Statuses: Draft / Applying / Waiting for Approval (by stage) / Sent Back / Rejected / Approved / Expired."
A36: KT-STS-003 | B36: Status | C36: Rejected status display | D36: Verify rejected status display | E36: Basic | F36: Manager rejects a submission | G36: 1. Login staff@gmail.com → New Submission: 'Status Test - To Be Rejected', Low, QA (fill remaining) 2. Switch to manager@gmail.com → find submission, open detail 3. Click red Reject → enter 'Test rejection' → Confirm 4. Switch to staff@gmail.com → view on dashboard and detail | H36: 'Rejected' badge with red color and XCircle icon. Rejection reason 'Test rejection' visible in Timeline tab. | I36: (none) | J36: P2 | K36: Passed | L36: https://jam.dev/c/2b43d3c6-f2ad-4a1d-984e-ee7d4b8bd278 | N36: Spec 6.3, Spec 9 (UI/UX) → "Statuses: Draft / Applying / Waiting for Approval (by stage) / Sent Back / Rejected / Approved / Expired."
A37: KT-STS-004 | B37: Status | C37: Need revision status display | D37: Verify need_revision status display | E37: Basic | F37: Manager requests revision | G37: 1. Login staff@gmail.com → New Submission: 'Status Test - Needs Revision', Low, QA (fill remaining) 2. Switch to manager@gmail.com → find submission, open detail 3. Click 'Request Revision' → enter 'Please add more details about the budget' → Confirm 4. Switch to staff@gmail.com → view on dashboard and detail | H37: 'Need Revision' badge with orange/yellow styling. Manager's feedback in Timeline tab. Edit button available for staff. | I37: (none) | J37: P2 | K37: Failed | M37: Not implemented? | N37: Spec 6.3, Spec 9 (UI/UX) → "Statuses: Draft / Applying / Waiting for Approval (by stage) / Sent Back / Rejected / Approved / Expired."
A38: KT-STS-005 | B38: Status | C38: Cancelled status display | D38: Verify cancelled status after owner cancels | E38: Basic | F38: Staff cancels own submission | G38: 1. Login staff@gmail.com → New Submission: 'Status Test - To Be Cancelled', Low, QA (fill remaining) 2. Find pending submission on dashboard → detail /approval-requests/[id] 3. Click Cancel (or equivalent withdraw action) 4. Verify status on dashboard and detail | H38: 'Cancelled' badge with grey styling. Submission no longer in active/pending lists. No further actions available. | I38: (none) | J38: P2 | K38: Failed | M38: Not implemented? | N38: Spec 6.3, Spec 9 (UI/UX) → "Statuses: Draft / Applying / Waiting for Approval (by stage) / Sent Back / Rejected / Approved / Expired."
A39: KT-ROL-001 | B39: User Role | C39: Staff sees own submissions | D39: Staff sees only own submissions on dashboard | E39: Main | F39: Multiple users have submissions | G39: 1. Login manager@gmail.com → submit ringi: 'Manager's Test Submission', Low, Management (if not already done) 2. Logout → login staff@gmail.com 3. Go to dashboard → check all visible submission cards | H39: Staff sees only OWN submissions. 'Manager's Test Submission' NOT visible. No other users' submissions. | I39: (none) | J39: P1 | K39: Partial Pass | L39: https://jam.dev/c/c778d93c-439e-47df-9600-95ef39426796 | M39: Client Side (FE side) Bug, after changin the role, the previous role submission still appear | N39: Spec 6.7 (Permissions), Spec 3 (Stakeholders) → "RBAC: Initiators edit/view their own applications, approvers operate on assigned cases, admins view all and change settings."
A40: KT-ROL-002 | B40: User Role | C40: Manager sees all + can approve | D40: Manager sees all submissions and can approve | E40: Main | F40: Submissions from multiple users exist | G40: 1. Login manager@gmail.com 2. Go to dashboard → check visible submission cards 3. Click any pending submission → detail /approval-requests/[id] 4. Check available action buttons | H40: Manager sees submissions from ALL users. Green Approve and red Reject buttons on pending submissions. | I40: (none) | J40: P1 | K40: Failed | M40: manager cannot see staff currently | N40: Spec 6.7 (Permissions), Spec 3 (Stakeholders) → "RBAC: Initiators edit/view their own applications, approvers operate on assigned cases, admins view all and change settings."
A41: KT-ROL-003 | B41: User Role | C41: Staff no approve buttons | D41: Staff cannot see approve/reject buttons | E41: Basic | F41: Pending submissions exist | G41: 1. Login staff@gmail.com 2. Click any own submission → detail /approval-requests/[id] 3. Check ALL available action buttons 4. Also check dashboard card actions | H41: No Approve, Reject, or Request Revision buttons. Staff only sees: Edit (on pending), Cancel (if available), View. | I41: (none) | J41: P1 | K41: Passed | N41: Spec 6.7 (Permissions), Spec 3 (Stakeholders) → "RBAC: Initiators edit/view their own applications, approvers operate on assigned cases, admins view all and change settings."
A42: KT-ROL-004 | B42: User Role | C42: Manager quick-approve | D42: Manager quick-approve from dashboard card | E42: Basic | F42: Pending submissions on dashboard | G42: 1. Login manager@gmail.com 2. Go to dashboard → find pending ringi card 3. Look for quick-action buttons on card 4. If available, use quick-approve | H42: Quick-approve exists on cards (if implemented). Approval succeeds from dashboard. Card status updates immediately. | I42: (none) | J42: P2 | K42: Passed | N42: Spec 6.7 (Permissions), Spec 3 (Stakeholders) → "RBAC: Initiators edit/view their own applications, approvers operate on assigned cases, admins view all and change settings."
A43: KT-ROL-005 | B43: User Role | C43: Staff admin URL access | D43: Staff direct URL access to admin page | E43: Edge Case | F43: Login as staff@gmail.com | G43: 1. Login staff@gmail.com 2. Type URL: https://eb-filemg-development.vercel.app/superadmin/dashboard → Enter 3. Observe result 4. Also try: https://eb-filemg-development.vercel.app/superadmin/users | H43: Staff NOT able to access admin pages. Redirected to / or access denied. No admin functionality exposed. No admin nav in sidebar. | I43: (none) | J43: P1 | K43: Passed | L43: https://jam.dev/c/39a8da64-75f7-4bfa-bdf1-288fce1229be | N43: Spec 6.7 (Permissions), Spec 3 (Stakeholders) → "RBAC: Initiators edit/view their own applications, approvers operate on assigned cases, admins view all and change settings."
A44: KT-ROL-006 | B44: User Role | C44: Accountant view-only | D44: Accountant views but cannot act on submissions | E44: Edge Case | F44: Accountant role exists | G44: 1. Check if accountant test account exists 2. If yes, login with accountant credentials 3. Go to dashboard → navigate to submission detail /approval-requests/[id] 4. Check available actions | H44: Accountant can VIEW submissions but cannot approve/reject/edit. No action buttons. View-only access. | I44: (none) | J44: P3 | K44: Failed | L44: https://jam.dev/c/76d1929b-f41c-4138-be8a-b6d24c036407 | M44: empty ringi on accountant | N44: Spec 6.7 (Permissions), Spec 3 (Stakeholders) → "RBAC: Initiators edit/view their own applications, approvers operate on assigned cases, admins view all and change settings."
A45: KT-AIC-009 | B45: AI Chat | C45: Upload doc, AI creates submission | D45: Upload ringi doc in chat, AI extracts data and creates submission | E45: Main | F45: Login as staff@gmail.com | G45: 1. Login staff@gmail.com 2. Go to new chat at / 3. Click paperclip → select ringi_en_form_laptop_purchase.docx 4. Verify file appears as attachment 5. Type: "Create a submission from this document" 6. Send and wait for response 7. Review extracted data | H45: AI extracts key data (title, amount ~$6,000, vendor, dept: Engineering). Offers pre-populated submission. Data matches document. | I45: ringi_en_form_laptop_purchase.docx | J45: P1 | K45: Passed | L45: https://jam.dev/c/1efadd9c-aaeb-4818-8f43-f1cdaa356980 | N45: Spec 5 (Business Flow), Spec 6.1, Spec 6.4 → "Contextual input assistance: Summarize chat messages to suggest initial form values."
A46: KT-AIC-010 | B46: AI Chat | C46: Upload multiple files in chat | D46: Upload multiple files simultaneously in AI chat | E46: Basic | F46: Login as staff@gmail.com | G46: 1. Login staff@gmail.com 2. Go to new chat at / 3. Click paperclip → select both: ringi_en_detailed_license_renewal.docx and ringi_en_purchase_monitors.docx 4. Verify both appear as previews 5. Type: "Please summarize both documents" 6. Send and review response | H46: Both files upload. AI acknowledges both. Separate summaries: Adobe license/$12,500 and Dell monitors/$3,750. | I46: ringi_en_detailed_license_renewal.docx, ringi_en_purchase_monitors.docx | J46: P2 | K46: Partial Pass | L46: https://jam.dev/c/e9294356-f4ce-4bcb-92b1-fa3317f70460 | M46: is it considered as 1 ringi or 2 ringi? can AI smartly categorize between same ringin file or different ringi file? | N46: Spec 6.1, Spec 6.4 → "Attachments: Quotes, contracts, and related materials. No tampering allowed after approval (must re-apply as a new version)."
A47: KT-AIC-011 | B47: AI Chat | C47: File card actions in chat | D47: File card actions in chat (Open/Share/Delete) | E47: Basic | F47: Login as staff@gmail.com | G47: 1. Login staff@gmail.com 2. Go to new chat at / 3. Click paperclip → select ringi_en_form_laptop_purchase.docx 4. Type: "What is this file about?" 5. Send and wait for response 6. Check file card in chat: action buttons (Open, Share) 7. Click Open → file opens 8. Click Share → link copied | H47: File card displayed with file name/type. Open button opens file. Share button copies share link. UI clear and consistent. | I47: ringi_en_form_laptop_purchase.docx | J47: P2 | K47: Partial Pass | L47: https://jam.dev/c/23f297ee-bd19-42be-93c5-3d59a25b1c86 | M47: there is bug that the file atteched is 0 even though it is submitted for the requirement it is debatable the test cases perhaps should be updated also why upload through "Drag & drop files here or click to browse - Max 20MB per file - Up to 10 files Supported: PDF, DOCX, XLSX, PPTX, CSV, TXT, MD, JPG, PNG, HEIC, ZIP" have different flow? | N47: Spec 6.4, Spec 9 (UI/UX) → "Approve/send back from chat cards."
A48: KT-AIC-012 | B48: AI Chat | C48: Search uploaded files via AI | D48: Search for uploaded files via AI chat | E48: Basic | F48: Login as staff@gmail.com, files previously uploaded | G48: 1. Login staff@gmail.com (files previously uploaded) 2. Go to new chat at / 3. Type: "Find my uploaded documents" 4. Send and review response 5. Check for SearchResultsCard with file cards | H48: AI uses search/retrieval for previously uploaded files. SearchResultsCard with file cards showing Open/Share actions. | I48: (none) | J48: P2 | K48: Passed | L48: https://jam.dev/c/3572f7bd-7456-4791-8ec0-424054bd2190 | N48: Spec 6.5, Spec 6.4 → "Search/filter by Ringi ID, subject, applicant, department, amount range, status, and period."
A49: KT-AIC-013 | B49: AI Chat | C49: Quick action card usage | D49: Use quick action card "Create submission from docs" | E49: Basic | F49: Login as staff@gmail.com | G49: 1. Login staff@gmail.com 2. Go to new chat at / (empty state) 3. Observe 3 action cards: 'Create submission from docs', 'Find approval evidence', 'Review submission status' 4. Click 'Create submission from docs' 5. Follow AI prompt → upload ringi_en_form_laptop_purchase.docx 6. Review AI workflow | H49: All 3 action cards visible. Clicking triggers AI workflow. AI prompts for doc upload. After uploading, AI processes for submission creation. | I49: (none) | J49: P2 | K49: Passed | L49: https://jam.dev/c/b29bbd40-08df-40c9-aa35-c1ede9fad64a | N49: Spec 5 (Business Flow), Spec 6.4, Spec 9 (UI/UX) → "Initiator opens the Ringi initiation form via chat, enters required items and attachments, and submits."

Sheet テストケース
A1: テストケースID | B1: カテゴリ | C1: 機能 | D1: テストケースタイトル | E1: 前提条件 | F1: テスト手順 | G1: 期待結果 | H1: 優先度 | I1: 実装状況 | J1: 備考 | K1: URL | L1: 合否 | M1: リンク | N1: 備考 | O1: 仕様書参照
A2: TC-SUB-001 | B2: 申請 | C2: フォーム項目 | D2: 全必須項目を入力して稟議を申請 | E2: 従業員としてログイン済み | F2: 1. アプリURLに移動する 2. 「新規申請」ボタンをクリック 3. タイトルを入力: 'Office Supplies Purchase' 4. カテゴリを選択: 'Purchasing' 5. 取引先名を入力: 'ABC Corp' 6. 項目を追加: Name='Printer', Qty=2, Amount=50000 7. 優先度を選択: 'High' 8. 期限日を設定 9. 部門を入力: 'Engineering' 10. 購入理由を入力 11. 目的を入力 12. 「送信」をクリック | G2: ステータス「保留中」で稟議が作成される. ダッシュボードにカードが表示される. アクティビティログに作成が記録される. | H2: P1 | I2: 実装済み | J2: 現在のフォーム項目で基本的な申請フローが動作 | K2: https://eb-filemg-development.vercel.app | L2: N/A | O2: Spec 6.1 (申請) → "フォーム項目: Subject, Category (Purchasing, Contracts, Expenses, Misc.), Amount (tax incl./excl.), Tax category, Payment terms, Vendor/Counterparty, Purpose, Period, Budget code, Project, Desired approval date, Applicant/Department."
A3: TC-SUB-002 | B3: 申請 | C3: 税計算 | D3: 税込計算で稟議を申請 | E3: ログイン済み、カテゴリは購買 | F3: 1. 「新規申請」をクリック 2. カテゴリを選択: 'Purchasing' 3. 「税金を使用」をONに切り替え 4. 「税込」に切り替え 5. 税率を入力: 10% 6. 項目を追加: Amount=110000 7. 残りの必須項目を入力 8. 「送信」をクリック | G3: 税金が正しく計算される. 金額が税込ラベルで表示される. 合計が税計算を反映する. | H3: P2 | I3: 実装済み | J3: 税金切替は購買カテゴリでのみ表示 | K3: https://eb-filemg-development.vercel.app | L3: N/A | O3: Spec 6.1 (申請) → "フォーム項目: Subject, Category (Purchasing, Contracts, Expenses, Misc.), Amount (tax incl./excl.), Tax category, Payment terms, Vendor/Counterparty, Purpose, Period, Budget code, Project, Desired approval date, Applicant/Department."
A4: TC-SUB-003 | B4: 申請 | C4: 税計算 | D4: 税抜計算で稟議を申請 | E4: ログイン済み、カテゴリは購買 | F4: 1. 「新規申請」をクリック 2. カテゴリを選択: 'Purchasing' 3. 「税金を使用」をONに切り替え 4. 「税抜」に切り替え 5. 税率を入力: 10% 6. 項目を追加: Amount=100000 7. 残りの必須項目を入力 8. 「送信」をクリック | G4: Tax calculated on top of amount. 税抜金額 + 税 = 合計が表示される. | H4: P2 | I4: 実装済み | J4: 税抜は基本金額に税金を加算 | K4: https://eb-filemg-development.vercel.app | L4: N/A | O4: Spec 6.1 (申請) → "フォーム項目: Subject, Category (Purchasing, Contracts, Expenses, Misc.), Amount (tax incl./excl.), Tax category, Payment terms, Vendor/Counterparty, Purpose, Period, Budget code, Project, Desired approval date, Applicant/Department."
A5: TC-SUB-004 | B5: 申請 | C5: 明細項目 | D5: 複数明細項目で稟議を申請 | E5: ログイン済み | F5: 1. 「新規申請」をクリック 2. 必須項目を入力 3. 項目1を追加: 'Laptop', Qty=5, Amount=200000 4. 「項目追加」をクリック 5. 項目2を追加: 'Mouse', Qty=5, Amount=5000 6. 「項目追加」をクリック 7. 項目3を追加: 'Keyboard', Qty=5, Amount=8000 8. 合計が自動計算されることを確認 9. 「送信」をクリック | G5: 3つの項目すべてが保存される. Total amount = (200000x5 + 5000x5 + 8000x5) = 1,065,000. 詳細ページに項目テーブルが正しく表示される. | H5: P2 | I5: 実装済み | J5: 項目はJSONB配列として保存 | K5: https://eb-filemg-development.vercel.app | L5: N/A | O5: Spec 6.1 (申請) → "フォーム項目: Subject, Category (Purchasing, Contracts, Expenses, Misc.), Amount (tax incl./excl.), Tax category, Payment terms, Vendor/Counterparty, Purpose, Period, Budget code, Project, Desired approval date, Applicant/Department."
A6: TC-SUB-005 | B6: 申請 | C6: バリデーション | D6: 必須項目未入力で稟議を申請（バリデーション） | E6: ログイン済み | F6: 1. 「新規申請」をクリック 2. タイトルを空のままにする 3. 取引先名を空のままにする 4. 項目を追加しない 5. 「送信」をクリック | G6: 全必須項目にフォームバリデーションエラーが表示される. 申請がブロックされる. 現在の言語でエラーメッセージが表示される (EN/JA). | H6: P1 | I6: 実装済み | J6: Yupバリデーションスキーマが必須項目を強制 | K6: https://eb-filemg-development.vercel.app | L6: N/A | O6: Spec 6.1 (申請) → "フォーム項目: Subject, Category (Purchasing, Contracts, Expenses, Misc.), Amount (tax incl./excl.), Tax category, Payment terms, Vendor/Counterparty, Purpose, Period, Budget code, Project, Desired approval date, Applicant/Department."
A7: TC-SUB-006 | B7: 申請 | C7: 添付ファイル | D7: 書類添付付きで稟議を申請 | E7: ログイン済み、システムにドキュメントが存在 | F7: 1. 「新規申請」をクリック 2. 必須項目をすべて入力 3. In attachments section, upload a PDF file 4. 2つ目の画像ファイルをアップロード 5. 「送信」をクリック 6. に移動する detail page | G7: 両方の添付ファイルが稟議にリンクされる. 詳細ページにダウンロードリンク付きファイルカードが表示される. | H7: P2 | I7: 実装済み | J7: approval_request_documents結合テーブルを使用 | K7: https://eb-filemg-development.vercel.app | L7: N/A | O7: Spec 6.1 (申請) → "添付ファイル: Quotes, contracts, and related materials. 承認後の改ざん不可（新バージョンとして再申請が必要）."
A8: TC-SUB-008 | B8: 申請 | C8: フォーム項目 | D8: フォームに予算コード項目が存在するか確認 | E8: ログイン済み | F8: 1. 「新規申請」をクリック 2. を探す 'Budget Code' field in the form 3. 予算コードの値を入力 | G8: Budget Code 項目が存在し入力可能. 値が稟議と共に保存される. | H8: P3 | I8: 未実装 | J8: 仕様書セクション8にbudget_codeが必要。現在のスキーマにはない。 | K8: https://eb-filemg-development.vercel.app | L8: N/A | O8: Spec 6.1 (申請) → "フォーム項目: Subject, Category (Purchasing, Contracts, Expenses, Misc.), Amount (tax incl./excl.), Tax category, Payment terms, Vendor/Counterparty, Purpose, Period, Budget code, Project, Desired approval date, Applicant/Department."
A9: TC-SUB-009 | B9: 申請 | C9: フォーム項目 | D9: フォームにプロジェクトコード項目が存在するか確認 | E9: ログイン済み | F9: 1. 「新規申請」をクリック 2. を探す 'Project Code' field in the form 3. プロジェクトコードの値を入力 | G9: Project Code 項目が存在し入力可能. 値が稟議と共に保存される. | H9: P3 | I9: 未実装 | J9: 仕様書セクション8にproject_codeが必要。現在のスキーマにはない。 | K9: https://eb-filemg-development.vercel.app | L9: N/A | O9: Spec 6.1 (申請) → "フォーム項目: Subject, Category (Purchasing, Contracts, Expenses, Misc.), Amount (tax incl./excl.), Tax category, Payment terms, Vendor/Counterparty, Purpose, Period, Budget code, Project, Desired approval date, Applicant/Department."
A10: TC-SUB-010 | B10: 申請 | C10: フォーム項目 | D10: フォームに通貨項目が存在するか確認 | E10: ログイン済み | F10: 1. 「新規申請」をクリック 2. を探す 'Currency' selector in the form 3. 異なる通貨を選択 (JPY, USD, etc.) | G10: 通貨フィールドにオプション（JPY、USDなど）が存在。選択した通貨が稟議に保存される。 | H10: P3 | I10: 未実装 | J10: 仕様書セクション8にcurrencyが必要。現在のスキーマにはない。 | K10: https://eb-filemg-development.vercel.app | L10: N/A | O10: Spec 6.1 (申請) → "フォーム項目: Subject, Category (Purchasing, Contracts, Expenses, Misc.), Amount (tax incl./excl.), Tax category, Payment terms, Vendor/Counterparty, Purpose, Period, Budget code, Project, Desired approval date, Applicant/Department."
A11: TC-SUB-011 | B11: 申請 | C11: フォーム項目 | D11: 開始日・終了日（期間）項目の確認 | E11: ログイン済み | F11: 1. 「新規申請」をクリック 2. を探す 'Start Date' and 'End Date' (Period) fields 3. 両方の日付を設定 | G11: Both start and end date fields 期間指定のために存在する. 値が保存される. | H11: P3 | I11: 未実装 | J11: 現在のコードには単一の'date'フィールドのみ。仕様ではstart_dateとend_dateが必要。 | K11: https://eb-filemg-development.vercel.app | L11: N/A | O11: Spec 6.1 (申請) → "フォーム項目: Subject, Category (Purchasing, Contracts, Expenses, Misc.), Amount (tax incl./excl.), Tax category, Payment terms, Vendor/Counterparty, Purpose, Period, Budget code, Project, Desired approval date, Applicant/Department."
A12: TC-SUB-012 | B12: 申請 | C12: フォーム項目 | D12: 希望承認日項目の確認 | E12: ログイン済み | F12: 1. 「新規申請」をクリック 2. を探す 'Desired Approval Date' field 3. Select a date | G12: Desired approval date field present and selectable. 値が稟議と共に保存される. | H12: P3 | I12: 未実装 | J12: 仕様書セクション8にdesired_approval_dateが必要。現在のスキーマにはない。 | K12: https://eb-filemg-development.vercel.app | L12: N/A | O12: Spec 6.1 (申請) → "フォーム項目: Subject, Category (Purchasing, Contracts, Expenses, Misc.), Amount (tax incl./excl.), Tax category, Payment terms, Vendor/Counterparty, Purpose, Period, Budget code, Project, Desired approval date, Applicant/Department."
A13: TC-SUB-013 | B13: 申請 | C13: 下書き | D13: 稟議を下書き保存 | E13: ログイン済み | F13: 1. 「新規申請」をクリック 2. 一部の項目を部分的に入力 3. 「下書き保存」をクリック 4. ステータスが表示されることを確認 'Draft' 5. 後で戻る and 下書きを編集 6. 下書きを送信 | G13: ステータス「下書き」で稟議が保存される. 下書きバッジ付きでダッシュボードに表示される. 承認者には表示されない. 後で編集して送信可能. | H13: P2 | I13: 未実装 | J13: 現在のシステムに「下書き」ステータスなし。仕様では初期状態としてDraftを要求。 | K13: https://eb-filemg-development.vercel.app | L13: N/A | O13: Spec 6.1 (申請) → "ステータス: Draft / Applying / Waiting for Approval (by stage) / Sent Back / Rejected / Approved / Expired."
... A108: TC-PDF-003 | B108: PDF生成 | C108: S3ストレージ | D108: PDFがメタデータタグ付きでS3に保存されるか確認 | E108: 完了PDFが生成済み | F108: 1. S3バケットで生成されたPDFを確認 2. 確認する metadata tags applied (ringi_id, category, department, approved_date) 3. 確認する S3 object key follows naming convention | G108: メタデータタグ付きでPDFがS3に保存される. アクセシブル via presigned URL. | H108: P3 | I108: 未実装 | J108: 完了PDF用のS3メタデータタグ付けなし。 | K108: https://eb-filemg-development.vercel.app | L108: N/A | O108: Spec 6.3 (承認操作) → "完了した稟議のPDFと添付ファイルをメタデータ付きでS3に保存."

Sheet サマリー
A1: テストケース — 仕様実装カバレッジ
A2: カテゴリ | B2: 合計 | C2: 実装済み | D2: 一部実装 | E2: 未実装 | F2: カバレッジ %
A3: 申請 | B3: =COUNTIF('テストケース'!B:B,A3) | C3: =COUNTIFS('テストケース'!B:B,A3,'テストケース'!I:I,"実装済み") | D3: =COUNTIFS('テストケース'!B:B,A3,'テストケース'!I:I,"一部実装") | E3: =B3-C3-D3 | F3: =IF(B3=0,0,(C3+D3*0.5)/B3)
A4: 承認ルート | B4: =COUNTIF('テストケース'!B:B,A4) | C4: =COUNTIFS('テストケース'!B:B,A4,'テストケース'!I:I,"実装済み") | D4: =COUNTIFS('テストケース'!B:B,A4,'テストケース'!I:I,"一部実装") | E4: =B4-C4-D4 | F4: =IF(B4=0,0,(C4+D4*0.5)/B4)
A5: 承認操作 | B5: =COUNTIF('テストケース'!B:B,A5) | C5: =COUNTIFS('テストケース'!B:B,A5,'テストケース'!I:I,"実装済み") | D5: =COUNTIFS('テストケース'!B:B,A5,'テストケース'!I:I,"一部実装") | E5: =B5-C5-D5 | F5: =IF(B5=0,0,(C5+D5*0.5)/B5)
A6: 通知 | B6: =COUNTIF('テストケース'!B:B,A6) | C6: =COUNTIFS('テストケース'!B:B,A6,'テストケース'!I:I,"実装済み") | D6: =COUNTIFS('テストケース'!B:B,A6,'テストケース'!I:I,"一部実装") | E6: =B6-C6-D6 | F6: =IF(B6=0,0,(C6+D6*0.5)/B6)
A7: 検索・参照 | B7: =COUNTIF('テストケース'!B:B,A7) | C7: =COUNTIFS('テストケース'!B:B,A7,'テストケース'!I:I,"実装済み") | D7: =COUNTIFS('テストケース'!B:B,A7,'テストケース'!I:I,"一部実装") | E7: =B7-C7-D7 | F7: =IF(B7=0,0,(C7+D7*0.5)/B7)
A8: レポート | B8: =COUNTIF('テストケース'!B:B,A8) | C8: =COUNTIFS('テストケース'!B:B,A8,'テストケース'!I:I,"実装済み") | D8: =COUNTIFS('テストケース'!B:B,A8,'テストケース'!I:I,"一部実装") | E8: =B8-C8-D8 | F8: =IF(B8=0,0,(C8+D8*0.5)/B8)
A9: 権限・セキュリティ | B9: =COUNTIF('テストケース'!B:B,A9) | C9: =COUNTIFS('テストケース'!B:B,A9,'テストケース'!I:I,"実装済み") | D9: =COUNTIFS('テストケース'!B:B,A9,'テストケース'!I:I,"一部実装") | E9: =B9-C9-D9 | F9: =IF(B9=0,0,(C9+D9*0.5)/B9)
A10: UI/UX | B10: =COUNTIF('テストケース'!B:B,A10) | C10: =COUNTIFS('テストケース'!B:B,A10,'テストケース'!I:I,"実装済み") | D10: =COUNTIFS('テストケース'!B:B,A10,'テストケース'!I:I,"一部実装") | E10: =B10-C10-D10 | F10: =IF(B10=0,0,(C10+D10*0.5)/B10)
A11: 非機能 | B11: =COUNTIF('テストケース'!B:B,A11) | C11: =COUNTIFS('テストケース'!B:B,A11,'テストケース'!I:I,"実装済み") | D11: =COUNTIFS('テストケース'!B:B,A11,'テストケース'!I:I,"一部実装") | E11: =B11-C11-D11 | F11: =IF(B11=0,0,(C11+D11*0.5)/B11)
A12: 管理・運用 | B12: =COUNTIF('テストケース'!B:B,A12) | C12: =COUNTIFS('テストケース'!B:B,A12,'テストケース'!I:I,"実装済み") | D12: =COUNTIFS('テストケース'!B:B,A12,'テストケース'!I:I,"一部実装") | E12: =B12-C12-D12 | F12: =IF(B12=0,0,(C12+D12*0.5)/B12)
A13: データモデル | B13: =COUNTIF('テストケース'!B:B,A13) | C13: =COUNTIFS('テストケース'!B:B,A13,'テストケース'!I:I,"実装済み") | D13: =COUNTIFS('テストケース'!B:B,A13,'テストケース'!I:I,"一部実装") | E13: =B13-C13-D13 | F13: =IF(B13=0,0,(C13+D13*0.5)/B13)
A14: PDF生成 | B14: =COUNTIF('テストケース'!B:B,A14) | C14: =COUNTIFS('テストケース'!B:B,A14,'テストケース'!I:I,"実装済み") | D14: =COUNTIFS('テストケース'!B:B,A14,'テストケース'!I:I,"一部実装") | E14: =B14-C14-D14 | F14: =IF(B14=0,0,(C14+D14*0.5)/B14)
A15: 合計 | B15: =SUM(B3:B14) | C15: =SUM(C3:C14) | D15: =SUM(D3:D14) | E15: =SUM(E3:E14) | F15: =IF(B15=0,0,(C15+D15*0.5)/B15)
A17: 実行可能テストケース — QAテスト結果
A18: カテゴリ | B18: 合計 | C18: 合格 | D18: 一部合格 | E18: 不合格 | F18: ブロック | G18: 合格率 %
A19: 申請 | B19: =COUNTIF('実行可能テストケース'!B:B,A19) | C19: =COUNTIFS('実行可能テストケース'!B:B,A19,'実行可能テストケース'!K:K,"合格") | D19: =COUNTIFS('実行可能テストケース'!B:B,A19,'実行可能テストケース'!K:K,"一部合格") | E19: =COUNTIFS('実行可能テストケース'!B:B,A19,'実行可能テストケース'!K:K,"不合格") | F19: =COUNTIFS('実行可能テストケース'!B:B,A19,'実行可能テストケース'!K:K,"ブロック") | G19: =IF((B19-F19)=0,0,(C19+D19*0.5)/(B19-F19))
A20: 承認 | B20: =COUNTIF('実行可能テストケース'!B:B,A20) | C20: =COUNTIFS('実行可能テストケース'!B:B,A20,'実行可能テストケース'!K:K,"合格") | D20: =COUNTIFS('実行可能テストケース'!B:B,A20,'実行可能テストケース'!K:K,"一部合格") | E20: =COUNTIFS('実行可能テストケース'!B:B,A20,'実行可能テストケース'!K:K,"不合格") | F20: =COUNTIFS('実行可能テストケース'!B:B,A20,'実行可能テストケース'!K:K,"ブロック") | G20: =IF((B20-F20)=0,0,(C20+D20*0.5)/(B20-F20))
A21: AIチャット | B21: =COUNTIF('実行可能テストケース'!B:B,A21) | C21: =COUNTIFS('実行可能テストケース'!B:B,A21,'実行可能テストケース'!K:K,"合格") | D21: =COUNTIFS('実行可能テストケース'!B:B,A21,'実行可能テストケース'!K:K,"一部合格") | E21: =COUNTIFS('実行可能テストケース'!B:B,A21,'実行可能テストケース'!K:K,"不合格") | F21: =COUNTIFS('実行可能テストケース'!B:B,A21,'実行可能テストケース'!K:K,"ブロック") | G21: =IF((B21-F21)=0,0,(C21+D21*0.5)/(B21-F21))
A22: AI検索 | B22: =COUNTIF('実行可能テストケース'!B:B,A22) | C22: =COUNTIFS('実行可能テストケース'!B:B,A22,'実行可能テストケース'!K:K,"合格") | D22: =COUNTIFS('実行可能テストケース'!B:B,A22,'実行可能テストケース'!K:K,"一部合格") | E22: =COUNTIFS('実行可能テストケース'!B:B,A22,'実行可能テストケース'!K:K,"不合格") | F22: =COUNTIFS('実行可能テストケース'!B:B,A22,'実行可能テストケース'!K:K,"ブロック") | G22: =IF((B22-F22)=0,0,(C22+D22*0.5)/(B22-F22))
A23: ステータス | B23: =COUNTIF('実行可能テストケース'!B:B,A23) | C23: =COUNTIFS('実行可能テストケース'!B:B,A23,'実行可能テストケース'!K:K,"合格") | D23: =COUNTIFS('実行可能テストケース'!B:B,A23,'実行可能テストケース'!K:K,"一部合格") | E23: =COUNTIFS('実行可能テストケース'!B:B,A23,'実行可能テストケース'!K:K,"不合格") | F23: =COUNTIFS('実行可能テストケース'!B:B,A23,'実行可能テストケース'!K:K,"ブロック") | G23: =IF((B23-F23)=0,0,(C23+D23*0.5)/(B23-F23))
A24: ユーザーロール | B24: =COUNTIF('実行可能テストケース'!B:B,A24) | C24: =COUNTIFS('実行可能テストケース'!B:B,A24,'実行可能テストケース'!K:K,"合格") | D24: =COUNTIFS('実行可能テストケース'!B:B,A24,'実行可能テストケース'!K:K,"一部合格") | E24: =COUNTIFS('実行可能テストケース'!B:B,A24,'実行可能テストケース'!K:K,"不合格") | F24: =COUNTIFS('実行可能テストケース'!B:B,A24,'実行可能テストケース'!K:K,"ブロック") | G24: =IF((B24-F24)=0,0,(C24+D24*0.5)/(B24-F24))
A25: 合計 | B25: =SUM(B19:B24) | C25: =SUM(C19:C24) | D25: =SUM(D19:D24) | E25: =SUM(E19:E24) | F25: =SUM(F19:F24) | G25: =IF((B25-F25)=0,0,(C25+D25*0.5)/(B25-F25))
A27: 凡例
A28: テストケースの実装状況：
A29: 実装済み = 仕様通りに実装完了 | 一部実装 = 一部機能あるが未完成 | 未実装 = 未着手
A30: カバレッジ % = (実装済み + 一部実装 × 0.5) / 合計
A32: 実行可能テストケースの合否：
A33: 合格 = テスト合格 | 一部合格 = 一部動作 | 不合格 = テスト失敗 | ブロック = テスト不可（前提条件未達）
A34: 合格率 % = (合格 + 一部合格 × 0.5) / (合計 − ブロック)
A37: 実行可能テストバグ — バグサマリー
A38: カテゴリ | B38: 合計 | C38: 重大 | D38: 重要 | E38: 軽微 | F38: バグ | G38: 改善提案
A39: 申請 | B39: =COUNTIF('実行可能テストバグ'!C:C,A39) | C39: =COUNTIFS('実行可能テストバグ'!C:C,A39,'実行可能テストバグ'!G:G,"重大") | D39: =COUNTIFS('実行可能テストバグ'!C:C,A39,'実行可能テストバグ'!G:G,"重要") | E39: =COUNTIFS('実行可能テストバグ'!C:C,A39,'実行可能テストバグ'!G:G,"軽微") | F39: =COUNTIFS('実行可能テストバグ'!C:C,A39,'実行可能テストバグ'!F:F,"バグ") | G39: =COUNTIFS('実行可能テストバグ'!C:C,A39,'実行可能テストバグ'!F:F,"改善提案")
A40: 承認 | B40: =COUNTIF('実行可能テストバグ'!C:C,A40) | C40: =COUNTIFS('実行可能テストバグ'!C:C,A40,'実行可能テストバグ'!G:G,"重大") | D40: =COUNTIFS('実行可能テストバグ'!C:C,A40,'実行可能テストバグ'!G:G,"重要") | E40: =COUNTIFS('実行可能テストバグ'!C:C,A40,'実行可能テストバグ'!G:G,"軽微") | F40: =COUNTIFS('実行可能テストバグ'!C:C,A40,'実行可能テストバグ'!F:F,"バグ") | G40: =COUNTIFS('実行可能テストバグ'!C:C,A40,'実行可能テストバグ'!F:F,"改善提案")
A41: AIチャット | B41: =COUNTIF('実行可能テストバグ'!C:C,A41) | C41: =COUNTIFS('実行可能テストバグ'!C:C,A41,'実行可能テストバグ'!G:G,"重大") | D41: =COUNTIFS('実行可能テストバグ'!C:C,A41,'実行可能テストバグ'!G:G,"重要") | E41: =COUNTIFS('実行可能テストバグ'!C:C,A41,'実行可能テストバグ'!G:G,"軽微") | F41: =COUNTIFS('実行可能テストバグ'!C:C,A41,'実行可能テストバグ'!F:F,"バグ") | G41: =COUNTIFS('実行可能テストバグ'!C:C,A41,'実行可能テストバグ'!F:F,"改善提案")
A42: AI検索 | B42: =COUNTIF('実行可能テストバグ'!C:C,A42) | C42: =COUNTIFS('実行可能テストバグ'!C:C,A42,'実行可能テストバグ'!G:G,"重大") | D42: =COUNTIFS('実行可能テストバグ'!C:C,A42,'実行可能テストバグ'!G:G,"重要") | E42: =COUNTIFS('実行可能テストバグ'!C:C,A42,'実行可能テストバグ'!G:G,"軽微") | F42: =COUNTIFS('実行可能テストバグ'!C:C,A42,'実行可能テストバグ'!F:F,"バグ") | G42: =COUNTIFS('実行可能テストバグ'!C:C,A42,'実行可能テストバグ'!F:F,"改善提案")
A43: ステータス | B43: =COUNTIF('実行可能テストバグ'!C:C,A43) | C43: =COUNTIFS('実行可能テストバグ'!C:C,A43,'実行可能テストバグ'!G:G,"重大") | D43: =COUNTIFS('実行可能テストバグ'!C:C,A43,'実行可能テストバグ'!G:G,"重要") | E43: =COUNTIFS('実行可能テストバグ'!C:C,A43,'実行可能テストバグ'!G:G,"軽微") | F43: =COUNTIFS('実行可能テストバグ'!C:C,A43,'実行可能テストバグ'!F:F,"バグ") | G43: =COUNTIFS('実行可能テストバグ'!C:C,A43,'実行可能テストバグ'!F:F,"改善提案")
A44: ユーザーロール | B44: =COUNTIF('実行可能テストバグ'!C:C,A44) | C44: =COUNTIFS('実行可能テストバグ'!C:C,A44,'実行可能テストバグ'!G:G,"重大") | D44: =COUNTIFS('実行可能テストバグ'!C:C,A44,'実行可能テストバグ'!G:G,"重要") | E44: =COUNTIFS('実行可能テストバグ'!C:C,A44,'実行可能テストバグ'!G:G,"軽微") | F44: =COUNTIFS('実行可能テストバグ'!C:C,A44,'実行可能テストバグ'!F:F,"バグ") | G44: =COUNTIFS('実行可能テストバグ'!C:C,A44,'実行可能テストバグ'!F:F,"改善提案")
A45: 合計 | B45: =SUM(B39:B44) | C45: =SUM(C39:C44) | D45: =SUM(D39:D44) | E45: =SUM(E39:E44) | F45: =SUM(F39:F44) | G45: =SUM(G39:G44)

Sheet 実行可能テストケース
A1: テストケースID | B1: カテゴリ | C1: 機能 | D1: テストケースタイトル | E1: 種別 | F1: 前提条件 | G1: テスト手順 | H1: 期待結果 | I1: テストファイル | J1: 優先度 | K1: 合否 | L1: リンク | M1: 備考 | N1: 仕様書参照
A2: KT-SUB-001 | B2: 申請 | C2: 英語ドキュメントで申請 | D2: 英語ドキュメントで有効な稟議を申請 | E2: メイン | F2: staff@gmail.comでログイン | G2: 1. Login staff@gmail.com at https://eb-filemg-development.vercel.app 2. 「新規申請」をクリック → Category: Purchasing 3. Title: 'Annual Software License Renewal', Priority: High, Dept: Sales 4. Add Item: 'Adobe CC Enterprise License' ×1, $12,500 5. Vendor: 'Adobe Inc.', Payment: 2026-03-15, Bank Transfer 6. Required by: 2026-03-01 09:00 7. Reason: 'Annual renewal of Adobe CC licenses, expires March 31' 8. Purpose: 'Maintain design tool access for Sales marketing' 9. Attach ringi_en_detailed_license_renewal.docx 10. 確認する Approval Route → Click 'Create Submission' | H2: 「保留中」ステータスで申請が作成される。タイトル='Annual Software License Renewal'、優先度=High、金額=$12,500。ファイルが添付され詳細表示で確認可能。承認ルートが表示される。 | I2: ringi_en_detailed_license_renewal.docx | J2: P1 | K2: 合格 | L2: https://jam.dev/c/c59ad198-fb75-4953-8e4c-279d811bdcc1 | M2: there is subtle bug: Submitted By Staff null --- It would be beneficial if there is Draft submission status as well | N2: Spec 6.1 (申請) → "フォーム項目: Subject, Category (Purchasing, Contracts, Expenses, Misc.), Amount (tax incl./excl.), Tax category, Payment terms, Vendor/Counterparty, Purpose, Period, Budget code, Project, Desired approval date, Applicant/Department."
A3: KT-SUB-002 | B3: 申請 | C3: 日本語ドキュメントで申請 | D3: 日本語ドキュメントで有効な稟議を申請 | E3: メイン | F3: staff@gmail.comでログイン | G3: 1. Login staff@gmail.com 2. New Submission → Category: Purchasing 3. Title: 'オフィスチェア購入稟議', Priority: Medium, Dept: 総務部 4. Add Item: 'エルゴノミクスオフィスチェア' ×10, ¥50,000 5. Enable Tax: ON, Rate: 10% 6. Vendor: 'オフィス家具株式会社', Payment: 2026-04-01, Bank Transfer 7. Required by: 2026-03-20 10:00 8. Reason: '総務部用オフィスチェア10脚の購入申請' 9. Purpose: '従業員の作業環境改善' 10. Attach ringi_jp_purchase_chairs.docx → Create Submission | H3: 日本語コンテンツで申請が作成され、文字化けなし。ステータス「保留中」。税: ¥500,000 + 10% = ¥550,000。ファイルが添付。 | I3: ringi_jp_purchase_chairs.docx | J3: P1 | K3: 合格 | L3: https://jam.dev/c/e7c5d836-7e67-4e76-82d7-9d8f3957ce0d | M3: there is subtle bug regarding the tax number in form and also in details | N3: Spec 6.1 (申請) → "フォーム項目: Subject, Category (Purchasing, Contracts, Expenses, Misc.), Amount (tax incl./excl.), Tax category, Payment terms, Vendor/Counterparty, Purpose, Period, Budget code, Project, Desired approval date, Applicant/Department."
A4: KT-SUB-003 | B4: 申請 | C4: 全項目＋明細項目で申請 | D4: 全項目＋複数明細で申請 | E4: メイン | F4: staff@gmail.comでログイン | G4: 1. Login staff@gmail.com 2. New Submission → Category: Purchasing 3. Title: 'Dell 4K Monitor Purchase for Development Team', Priority: Medium, Dept: IT 4. 項目1を追加: 'Dell UltraSharp U2723QE 27"' ×5, $750 5. 項目2を追加: 'Monitor Stand Arm' ×5, $0 6. Vendor: 'Dell Technologies', Payment: 2026-04-15, Credit Card 7. Required by: 2026-04-01 14:00 8. Reason: 'Purchase 5x 4K monitors for dev team' 9. Purpose: 'Improve developer productivity with high-res displays' 10. Remarks: 'Deliver to Building A, Floor 3' 11. Attach ringi_en_purchase_monitors.docx → Create Submission | H4: 全フィールドが保存。両方の品目が表示（モニター＋スタンド）。金額=$3,750。添付ファイルが表示・ダウンロード可能。ステータス「保留中」。 | I4: ringi_en_purchase_monitors.docx | J4: P1 | K4: 合格 | L4: https://jam.dev/c/e5777a3f-6626-4419-92d8-8884a9ef544d | M4: there is bug in detail when clicked the filed it show xml file | N4: Spec 6.1 (申請) → "フォーム項目: Subject, Category (Purchasing, Contracts, Expenses, Misc.), Amount (tax incl./excl.), Tax category, Payment terms, Vendor/Counterparty, Purpose, Period, Budget code, Project, Desired approval date, Applicant/Department."
A5: KT-SUB-004 | B5: 申請 | C5: 最小限の項目で申請 | D5: 最小限の必須項目のみで申請 | E5: 基本 | F5: staff@gmail.comでログイン | G5: 1. staff@gmail.comでログイン 2. 新規申請 → カテゴリ: Other 3. タイトル: 'Minimum Fields Test'、優先度: Low、部署: General 4. 品目なし、添付なし、備考なし 5. 取引先: 'N/A'、支払: 2026-05-01、Cash 6. 期限: 2026-04-30 17:00 7. 理由: 'Testing with minimum required fields only'、目的: 'Edge case test' 8. 承認ルート確認 → 「申請を作成」 | H5: 必須データのみで申請が作成される。オプション項目でバリデーションエラーなし。ダッシュボードに「保留中」ステータス。 | I5: (none) | J5: P2 | K5: 合格 | L5: https://jam.dev/c/ca785d03-1021-4e40-987f-54b86a4660ea | N5: Spec 6.1 (申請) → "フォーム項目: Subject, Category (Purchasing, Contracts, Expenses, Misc.), Amount (tax incl./excl.), Tax category, Payment terms, Vendor/Counterparty, Purpose, Period, Budget code, Project, Desired approval date, Applicant/Department."
A6: KT-SUB-005 | B6: 申請 | C6: Excel添付で申請 | D6: Excelスプレッドシート稟議を添付して申請 | E6: 基本 | F6: staff@gmail.comでログイン | G6: 1. Login staff@gmail.com 2. New Submission → Category: Expense 3. Title: '会計ソフト更新', Priority: Medium, Dept: 経理部 4. Add Item: 'freee会計 年間ライセンス' ×1, ¥600,000 5. Vendor: 'freee株式会社', Payment: 2026-04-01, Bank Transfer 6. Required by: 2026-03-25 10:00 7. Reason: '経理部の会計ソフトfreeeの年間ライセンス更新' 8. Purpose: '経理業務の継続' 9. Attach ringi_jp_spreadsheet_accounting.xlsx → Create Submission | H6: Excelファイル（.xlsx）が添付として受け入れられる。申請が作成される。詳細表示からファイルをダウンロード可能。 | I6: ringi_jp_spreadsheet_accounting.xlsx | J6: P2 | K6: 合格 | L6: https://jam.dev/c/5a4cb745-883b-45d7-9be7-dfc259942d1f | N6: Spec 6.1 (申請) → "添付ファイル: Quotes, contracts, and related materials. 承認後の改ざん不可（新バージョンとして再申請が必要）."
A7: KT-SUB-006 | B7: 申請 | C7: 保留中の申請を編集 | D7: 保留中の申請を編集 | E7: 基本 | F7: staff@gmail.comによる保留中の申請が存在 | G7: 1. Login staff@gmail.com 2. Go to dashboard, click pending submission card → detail /approval-requests/[id] 3. 「編集」をクリック 4. Change title to 'Updated: [original title]' 5. Change Priority to Critical 6. 保存 changes | H7: 編集フォームが事前入力データで読み込まれる。変更が保存される。申請は「保留中」のまま。更新された値が詳細に表示。 | I7: (none) | J7: P2 | K7: 合格 | L7: https://jam.dev/c/d10f06f9-6592-48b7-bdd6-b8f727a38b55 | N7: Spec 6.1 (申請) → "ステータス: Draft / Applying / Waiting for Approval (by stage) / Sent Back / Rejected / Approved / Expired."
A8: KT-SUB-007 | B8: 申請 | C8: 画像ファイルで申請 | D8: ビーチ画像を添付して申請（不正ファイル形式） | E8: エッジケース | F8: staff@gmail.comでログイン | G8: 1. Login staff@gmail.com 2. New Submission → Category: Other 3. Title: 'Edge Case Test - Image Upload', Priority: Low, Dept: QA 4. Vendor: 'Test', Payment: 2026-05-01, Cash 5. Required by: 2026-04-30 17:00 6. Reason: 'Testing image file upload behavior', Purpose: 'QA Edge Case' 7. Attach edge_beach_image.jpg 8. を試みる submit | H8: システムが画像ファイルタイプを明確なメッセージで拒否するか、正常に受け入れる（クラッシュなし、データ破損なし）。 | I8: edge_beach_image.jpg | J8: P2 | K8: 合格 | L8: https://jam.dev/c/9809373a-1afa-4a8d-8540-e4836b18b2c5 | N8: Spec 6.1 (申請) → "添付ファイル: Quotes, contracts, and related materials. 承認後の改ざん不可（新バージョンとして再申請が必要）."
A9: KT-SUB-008 | B9: 申請 | C9: 空PDFで申請 | D9: 空白PDFを添付して申請 | E9: エッジケース | F9: staff@gmail.comでログイン | G9: 1. staff@gmail.comでログイン 2. 新規申請 → カテゴリ: Other 3. タイトル: 'Edge Case Test - Empty PDF'、優先度: Low、部署: QA 4. 取引先: 'Test'、支払: 2026-05-01、Cash 5. 期限: 2026-04-30 17:00 6. 理由: 'Testing empty PDF upload behavior'、目的: 'Edge case' 7. ペーパークリップ → edge_empty.pdf（空のPDF）を選択 8. 承認ルート確認 → 「申請を作成」 | H9: 空のPDFをクラッシュせずに処理。受け入れるか適切な警告を表示。 | I9: edge_empty_file.pdf | J9: P3 | K9: 合格 | L9: https://jam.dev/c/22a8a004-c862-44b8-9dbf-5c70b1825501 | N9: Spec 6.1 (申請) → "添付ファイル: Quotes, contracts, and related materials. 承認後の改ざん不可（新バージョンとして再申請が必要）."
A10: KT-SUB-009 | B10: 申請 | C10: 特殊文字ファイル名で申請 | D10: 日本語文字を含むファイル名で申請 | E10: エッジケース | F10: staff@gmail.comでログイン | G10: 1. Login staff@gmail.com 2. New Submission → Category: Other 3. Title: 'Edge Case Test - Special Characters', Priority: Low, Dept: QA 4. Vendor: 'Test', Payment: 2026-05-01, Cash 5. Required by: 2026-04-30 17:00 6. Reason: 'Testing special character filename handling', Purpose: 'QA Edge Case' 7. Attach edge_special_chars_名前.docx (JP chars in filename) 8. Click 'Create Submission' | H10: ファイルがアップロードされる。ファイル名の日本語文字が正しく保持・表示される。エラーなしで申請が作成。 | I10: edge_special_chars_名前.docx | J10: P2 | K10: 不合格 | L10: https://jam.dev/c/e9e24876-69bd-4c41-ba8b-0886be4cd867 | M10: error file char name | N10: Spec 6.1 (申請) → "添付ファイル: Quotes, contracts, and related materials. 承認後の改ざん不可（新バージョンとして再申請が必要）."
A11: KT-SUB-010 | B11: 申請 | C11: 超高額で申請 | D11: 超高額の金額で申請 | E11: エッジケース | F11: staff@gmail.comでログイン | G11: 1. staff@gmail.comでログイン 2. 新規申請 → カテゴリ: Other 3. タイトル: 'Edge Case Test - Large Amount'、優先度: Low、部署: QA 4. 品目追加: 'Large Amount Test Item' ×1、$999,999,999,999 5. 取引先: 'Test'、支払: 2026-05-01、Cash 6. 期限: 2026-04-30 17:00 7. 理由: 'Testing large amount handling' 8. 承認ルート確認 → 「申請を作成」 | H11: システムが大きな数値を受け入れるか、最大金額のバリデーションを表示。クラッシュやデータ破損なし。 | I11: (none) | J11: P3 | K11: 不合格 | L11: https://jam.dev/c/e7cb4064-6b39-4b65-a1e8-e609eef7f6e5 | M11: number overflow | N11: Spec 6.1 (申請) → "フォーム項目: Subject, Category (Purchasing, Contracts, Expenses, Misc.), Amount (tax incl./excl.), Tax category, Payment terms, Vendor/Counterparty, Purpose, Period, Budget code, Project, Desired approval date, Applicant/Department."
A12: KT-APR-001 | B12: 承認 | C12: 管理者が稟議を承認 | D12: 管理者が保留中の稟議を承認 | E12: メイン | F12: 保留中の申請が存在（スタッフが申請） | G12: 1. Login manager@gmail.com at https://eb-filemg-development.vercel.app 2. Find pending ringi card on dashboard 3. Click card → detail /approval-requests/[id] 4. Review Details tab, then Files tab 5. Click green Approve button 6. (Optional) Notes: 'Approved - budget within Q1 allocation' 7. 「確認」をクリック 8. Switch to staff@gmail.com → verify 'Approved' on dashboard | H12: ステータスが変更される: 'Approved'. Recorded with timestamp in Timeline tab. Green CheckCircle icon. Staff sees 'Approved'. | I12: (none) | J12: P1 | K12: 不合格 | L12: https://jam.dev/c/432754ce-879c-4937-a5a1-f315125385af | M12: There is glitch of approval with status and then it is empty (but there is workaround to login as staff first and then logout and then login as manager) | N12: Spec 6.3 (承認操作) → "ステータス: Draft / Applying / Waiting for Approval (by stage) / Sent Back / Rejected / Approved / Expired."
A13: KT-APR-002 | B13: 承認 | C13: 管理者が理由付きで却下 | D13: 管理者が却下理由付きで稟議を却下 | E13: メイン | F13: 保留中の申請が存在 | G13: 1. Login manager@gmail.com 2. Find pending ringi → detail /approval-requests/[id] 3. Click red Reject button 4. Try submitting without reason → verify validation error 5. Enter: 'Budget exceeded for Q1. Please reduce or defer to Q2.' 6. 「確認」をクリック | H13: 理由なしでバリデーションエラー。ステータス →「却下済み」XCircleアイコン付き。理由がタイムラインタブに表示。スタッフが却下理由を確認可能。 | I13: (none) | J13: P1 | K13: ブロック | L13: blocked of the KT-APR-001 | N13: Spec 6.3 (承認操作) → "差戻しと却下にはコメントが必須. 再申請時の差分メモ."
A14: KT-APR-003 | B14: 承認 | C14: 管理者が修正を依頼 | D14: 管理者が稟議を差戻し | E14: 基本 | F14: 保留中の申請が存在 | G14: 1. Login manager@gmail.com 2. Open pending ringi detail /approval-requests/[id] 3. Click 'Request Revision' / 'Send Back' 4. Enter: 'Please add detailed cost breakdown and attach vendor quotation.' 5. 「確認」をクリック | H14: ステータス →「要修正」。フィードバックがタイムラインタブに保存。スタッフがフィードバックと編集オプションを確認可能。 | I14: (none) | J14: P2 | K14: ブロック | L14: blocked of the KT-APR-001 | N14: Spec 6.3 (承認操作) → "差戻しと却下にはコメントが必須. 再申請時の差分メモ."
A15: KT-APR-004 | B15: 承認 | C15: スタッフが修正後再編集 | D15: 修正依頼後にスタッフが再編集・再申請 | E15: 基本 | F15: 「要修正」ステータスの申請 | G15: 1. Login staff@gmail.com 2. Find 'Need Revision' submission on dashboard 3. Open detail /approval-requests/[id] → 「編集」をクリック 4. Update Reason with cost breakdown, adjust amount/items 5. Click 再申請 / 保存 | H15: Edit form loads with pre-filled data. Changes saved. ステータスが「保留中」に戻る for manager re-review. | I15: (none) | J15: P2 | K15: ブロック | L15: blocked of the KT-APR-001 | N15: Spec 6.3 (承認操作) → "差戻しと却下にはコメントが必須. 再申請時の差分メモ."
A16: KT-APR-005 | B16: 承認 | C16: スタッフの承認をブロック | D16: スタッフが承認を試行（ブロックされるべき） | E16: エッジケース | F16: 保留中の申請が存在 | G16: 1. staff@gmail.comでログイン 2. 保留中の申請の詳細 /approval-requests/[id] を開く 3. ページ上の全アクションボタンを確認 | H16: 承認、却下、修正依頼ボタンが表示されない。スタッフは詳細、ファイル、タイムラインのみ閲覧可能。 | I16: (none) | J16: P1 | K16: 合格 | L16: https://jam.dev/c/ee692561-c9db-4fc1-9f6c-a9befb6953f0 | N16: Spec 6.7 (権限・セキュリティ) → "ロールベースアクセス制御: 起案者は自分の申請を編集/閲覧, 承認者は割り当てられた案件を操作, 管理者は全件閲覧し設定変更."
A17: KT-APR-006 | B17: 承認 | C17: 二重承認の試行 | D17: 承認済み稟議の二重承認を試行 | E17: エッジケース | F17: 承認済みの申請 | G17: 1. Login manager@gmail.com 2. Open already-approved submission /approval-requests/[id] 3. 確認する Approve/Reject buttons are still available | H17: 承認済みの申請に承認/却下ボタンが利用不可。緑のCheckCircle付き「承認済み」。追加アクションなし。 | I17: (none) | J17: P3 | K17: ブロック | N17: Spec 6.3 (承認操作) → "ステータス: Draft / Applying / Waiting for Approval (by stage) / Sent Back / Rejected / Approved / Expired."
A18: KT-APR-007 | B18: 承認 | C18: 管理者の自己承認 | D18: 管理者が自分の稟議を承認しようとする | E18: エッジケース | F18: 管理者が自分の稟議を申請済み | G18: 1. manager@gmail.comでログイン 2. 新規申請 → カテゴリ: Other 3. タイトル: 'Manager Self-Approval Test'、優先度: Low、部署: Management 4. 取引先: 'Internal'、支払: 2026-05-01、Cash 5. 期限: 2026-04-30 17:00 6. 理由: 'Testing self-approval behavior' 7. 「申請を作成」で送信 8. ダッシュボードで自分の申請を見つける → 承認を試行 | H18: 実際の動作を記録: 自己承認が許可されるかブロックされるか？ブロック: 明確なエラー。許可: 正常に処理。 | I18: (none) | J18: P2 | K18: 合格 | L18: https://jam.dev/c/af2dced4-d706-4673-ac8d-6723520dce0f | M18: Clarify the Requirement | N18: Spec 6.3 (承認操作) → "ロールベースアクセス制御: 起案者は自分の申請を編集/閲覧, 承認者は割り当てられた案件を操作, 管理者は全件閲覧し設定変更."
A19: KT-APR-008 | B19: 承認 | C19: ダッシュボードからクイック承認 | D19: ダッシュボードカードからクイック承認 | E19: 基本 | F19: ダッシュボードに保留中の申請が表示 | G19: 1. Login manager@gmail.com 2. Go to dashboard 3. Find pending ringi card 4. を探す quick-approve action on card itself 5. If available, use quick-approve without opening detail | H19: カードにクイック承認アクションあり（実装されている場合）。ダッシュボードからの承認が成功。ステータスが即座に更新。 | I19: (none) | J19: P2 | K19: 合格 | N19: Spec 6.4 (チャット連携), Spec 9 (UI/UX) → "チャットカードから承認/差戻し."
A20: KT-AIC-001 | B20: AIチャット | C20: AIで稟議作成（英語） | D20: AIに英語で自然言語から稟議作成を依頼 | E20: メイン | F20: staff@gmail.comでログイン | G20: 1. staff@gmail.comでログイン 2. https://eb-filemg-development.vercel.app/ （新規チャット）にアクセス 3. 入力: "Create a ringi for purchasing 10 office laptops, total cost $15,000" 4. 送信してAI応答を待つ | H20: AIがタイトル、説明、金額（$15,000）を含む稟議ドラフトを生成。応答は英語。チャットスレッドが作成される（/c/[threadId]）。 | I20: (none) | J20: P1 | K20: 一部合格 | L20: https://jam.dev/c/3ff23937-7197-4d13-9381-65ef837e3113 | M20: AI generate pending, but not Draft it lead to user cannot edit the ringi when use try to edit the ringi, it got bugs | N20: Spec 5 (業務フロー), Spec 6.1, Spec 6.4 → "起案者がチャットから稟議起案フォームを開き、必要項目と添付を入力して送信."
A21: KT-AIC-002 | B21: AIチャット | C21: AIで稟議作成（日本語） | D21: AIに日本語で自然言語から稟議作成を依頼 | E21: メイン | F21: staff@gmail.comでログイン | G21: 1. Login staff@gmail.com 2. Go to new chat at / 3. Type: "ノートPC10台購入の稟議書を作成してください。合計金額150万円" 4. Send and wait for AI response | H21: AI generates ringi draft in Japanese with appropriate title and amount (¥1,500,000 / 150万円). | I21: (none) | J21: P1 | K21: 一部合格 | L21: https://jam.dev/c/37d7d204-3527-4e40-aad0-e51fab33d42a | M21: AI generate pending, but not Draft it lead to user cannot edit the ringi it got asking again and again same things | N21: Spec 5 (業務フロー), Spec 6.1, Spec 6.4 → "起案者がチャットから稟議起案フォームを開き、必要項目と添付を入力して送信."
A22: KT-AIC-003 | B22: AIチャット | C22: ドキュメントアップロード＋AI要約 | D22: 稟議ドキュメントをアップロードしAIに要約を依頼 | E22: 基本 | F22: staff@gmail.comでログイン | G22: 1. Login staff@gmail.com 2. Go to new chat at / 3. Click paperclip → select ringi_en_detailed_license_renewal.docx 4. 確認する file appears as attachment preview 5. Type: "Please summarize this ringi document" 6. Send and wait for response | H22: AIがドキュメントを処理。要約にAdobe CC / ライセンス更新、$12,500、Sales部門またはHanako Suzukiが言及される。内容に正確。 | I22: ringi_en_detailed_license_renewal.docx | J22: P1 | K22: 合格 | L22: https://jam.dev/c/d1706ed5-abf0-4a53-b19d-a1368e703521 | N22: Spec 6.1, Spec 6.4 (チャット連携) → "コンテキスト入力支援: チャットメッセージを要約してフォーム初期値を提案."
A23: KT-AIC-004 | B23: AIチャット | C23: 日本語でドキュメントについて質問 | D23: 日本語でアップロードしたドキュメントについてAIに質問 | E23: 基本 | F23: staff@gmail.comでログイン | G23: 1. Login staff@gmail.com 2. Go to new chat at / 3. Click paperclip → select ringi_jp_standard_salesforce.docx 4. Type: "この稟議書の内容を教えてください" 5. Send and review response | H23: AI responds in Japanese. Summary mentions Salesforce / 営業支援ツール, ¥4,100,000, 営業部 or 鈴木花子. | I23: ringi_jp_standard_salesforce.docx | J23: P2 | K23: 合格 | L23: https://jam.dev/c/40723d7b-aae3-47e5-81e3-d83304091945 | M23: there is UI glitch, also the loader is not appeared | N23: Spec 6.1, Spec 6.4 (チャット連携) → "コンテキスト入力支援: チャットメッセージを要約してフォーム初期値を提案."
A24: KT-AIC-005 | B24: AIチャット | C24: 稟議用に画像をアップロード | D24: ビーチ画像をアップロードしAIに稟議作成を依頼 | E24: エッジケース | F24: staff@gmail.comでログイン | G24: 1. staff@gmail.comでログイン 2. / で新規チャットにアクセス 3. ペーパークリップ → edge_beach_image.jpg（ビーチ写真）を選択 4. 入力: "Create a ringi from this document" 5. 送信して応答を確認 | H24: AIがクラッシュしない。ファイルが有効な稟議ドキュメントでないか、画像から情報を抽出できないことを示す。適切な応答。 | I24: edge_beach_image.jpg | J24: P2 | K24: 合格 | L24: https://jam.dev/c/f573209c-c362-421e-8cb7-e5367245fd4a | N24: Spec 6.1, Spec 6.4 (チャット連携) → "添付ファイル: Quotes, contracts, and related materials. 承認後の改ざん不可（新バージョンとして再申請が必要）."
A25: KT-AIC-006 | B25: AIチャット | C25: 無関係な質問 | D25: 無関係な質問やでたらめをAIに送信 | E25: エッジケース | F25: staff@gmail.comでログイン | G25: 1. staff@gmail.comでログイン 2. / で新規チャットにアクセス 3. 入力: "asdfghjkl what is the weather today?" 4. 送信して応答を確認 | H25: AIがクラッシュせずに応答。稟議関連のヘルプにリダイレクトするか、スコープについて丁寧に応答。 | I25: (none) | J25: P3 | K25: 合格 | L25: https://jam.dev/c/aea773c3-1e12-4378-9647-a6ae532b19d8 | N25: Spec 6.4 (チャット連携) → "コンテキスト入力支援: チャットメッセージを要約してフォーム初期値を提案."
A26: KT-AIC-007 | B26: AIチャット | C26: 非稟議ドキュメントで申請 | D26: 非稟議ドキュメントをアップロードし申請作成を依頼 | E26: エッジケース | F26: staff@gmail.comでログイン | G26: 1. staff@gmail.comでログイン 2. / で新規チャットにアクセス 3. ペーパークリップ → edge_large_file.pdf（稟議以外のコンテンツ）を選択 4. 入力: "Create a ringi submission from this" 5. 送信して応答を確認 | H26: AIがドキュメントを処理。可能な限り情報を抽出するか、稟議データがないことを示す。適切な応答。 | I26: edge_large_file.pdf | J26: P2 | K26: 合格 | L26: https://jam.dev/c/fa7689ce-95ec-4753-9c3c-7150f4b6a62a | N26: Spec 6.1, Spec 6.4 (チャット連携) → "コンテキスト入力支援: チャットメッセージを要約してフォーム初期値を提案."
A27: KT-AIC-008 | B27: AIチャット | C27: 複数ターンの会話 | D27: 複数ターンの会話で段階的に稟議を構築 | E27: 基本 | F27: staff@gmail.comでログイン | G27: 1. Login staff@gmail.com 2. Go to new chat at / 3. Msg 1: "I need to create a ringi for purchasing new office furniture" 4. を待つ response 5. Msg 2: "The budget is $8,000 for 10 standing desks from IKEA" 6. を待つ response 7. Msg 3: "Please finalize with department 'Operations' and requestor 'John Smith'" 8. Review final output | H27: AIが3ターンにわたりコンテキストを維持。最終稟議: 家具、$8,000、スタンディングデスク10台、IKEA、Operations、John Smith。同じスレッドURL。 | I27: (none) | J27: P2 | K27: 一部合格 | L27: https://jam.dev/c/3517856c-1367-41bc-af8b-43a0a096d508 | M27: should comply with minimum required fields | N27: Spec 5 (業務フロー), Spec 6.4 → "起案者がチャットから稟議起案フォームを開き、必要項目と添付を入力して送信."
A28: KT-AIR-001 | B28: AI検索 | C28: 申請ステータスを質問（英語） | D28: AIに英語で特定の申請ステータスを質問 | E28: メイン | F28: スタッフに既存の申請がある | G28: 1. staff@gmail.comでログイン（既存の申請あり） 2. 既存の申請タイトルを確認（例: 'Annual Software License Renewal'） 3. / で新規チャットにアクセス 4. 入力: "What is the status of 'Annual Software License Renewal'?" 5. 送信して応答を確認 | H28: AIが正しい申請を取得。現在のステータス（保留中/承認済みなど）を報告。情報がダッシュボードと一致。SearchResultsCardが表示される場合あり。 | I28: (none) | J28: P1 | K28: 一部合格 | L28: https://jam.dev/c/6dfb78f5-bb0d-4d70-a03a-929b74ae0e49 | M28: it show the correct summary, yet files shown pending submssion are too manies | N28: Spec 6.5 (検索・参照) → "稟議ID、件名、申請者、部門、金額範囲、ステータス、期間で検索/フィルタ."
A29: KT-AIR-002 | B29: AI検索 | C29: 名前でドキュメントを検索 | D29: AIに名前でドキュメント/申請を検索依頼 | E29: メイン | F29: システムにドキュメントが存在 | G29: 1. staff@gmail.comでログイン 2. / で新規チャットにアクセス 3. 入力: "Find the document called 'Dell 4K Monitor Purchase for Development Team'" 4. 送信して応答を確認 | H29: AIが申請を検索。ステータス、日付、金額情報を提供。Open/Shareボタン付きファイルカードのSearchResultsCard。 | I29: (none) | J29: P1 | K29: 不合格 | L29: https://jam.dev/c/07e3abd6-675a-4cbd-b172-39321f9f55ec | M29: search about monitor yet not shown | N29: Spec 6.5 (検索・参照) → "稟議ID、件名、申請者、部門、金額範囲、ステータス、期間で検索/フィルタ."
A30: KT-AIR-003 | B30: AI検索 | C30: 申請ステータスを確認 | D30: AIに申請ステータスの確認を依頼 | E30: 基本 | F30: スタッフに申請がある | G30: 1. staff@gmail.comでログイン（複数の申請あり） 2. / で新規チャットにアクセス 3. 入力: "Review and check my submission status" 4. 送信して応答を確認 | H30: AIがスタッフの申請を現在のステータスと共に一覧表示。リストが / のダッシュボードと一致。 | I30: (none) | J30: P2 | K30: 合格 | L30: https://jam.dev/c/d1931bae-8fb2-47b1-81f8-e6b126a3675b | M30: but should be have pagination like to avoid long time, if many files also the numbering shown always 1 (which is bug) | N30: Spec 6.5 (検索・参照) → "稟議ID、件名、申請者、部門、金額範囲、ステータス、期間で検索/フィルタ."
A31: KT-AIR-004 | B31: AI検索 | C31: 日本語で検索 | D31: 日本語でドキュメント/ステータスを検索 | E31: 基本 | F31: 日本語のドキュメントが存在 | G31: 1. Login staff@gmail.com (JP submissions exist) 2. Go to new chat at / 3. Type: "稟議書の状態を確認してください" 4. Send and review response | H31: AIが日本語で応答。申請をステータスと共に一覧表示。日本語タイトルが正しく表示。 | I31: (none) | J31: P2 | K31: 合格 | L31: https://jam.dev/c/c2455701-1403-4615-9574-15a0ea25ec9c | M31: pass yet buggy, 1st submit waiting so long, the sent message is not disabled thus can prompt 2 times, and the response appear two times | N31: Spec 6.5 (検索・参照) → "稟議ID、件名、申請者、部門、金額範囲、ステータス、期間で検索/フィルタ."
A32: KT-AIR-005 | B32: AI検索 | C32: 存在しないドキュメント | D32: 存在しないドキュメント/申請を問い合わせ | E32: エッジケース | F32: staff@gmail.comでログイン | G32: 1. staff@gmail.comでログイン 2. / で新規チャットにアクセス 3. 入力: "What is the status of ringi XYZ-NONEXISTENT-999?" 4. 送信して応答を確認 | H32: AIが捏造データを返さない。一致する申請が見つからないことを示す。タイトル確認または既存の一覧表示を提案。 | I32: (none) | J32: P2 | K32: 合格 | L32: https://jam.dev/c/b6fabc61-818c-473a-b6b5-d1a8bd6b611a | M32: Pass yet buggy, it give all pending requests | N32: Spec 6.5 (検索・参照) → "稟議ID、件名、申請者、部門、金額範囲、ステータス、期間で検索/フィルタ."
A33: KT-AIR-006 | B33: AI検索 | C33: 他ユーザーの申請 | D33: 他ユーザーの申請ステータスを問い合わせ | E33: エッジケース | F33: 複数ユーザーが申請を持っている | G33: 1. staff@gmail.comでログイン 2. / で新規チャットにアクセス 3. 入力: "What is the status of 'Manager Self-Approval Test'?" （管理者の申請） 4. 送信して応答を確認 | H33: AIがデータ境界を尊重。アクセスを拒否するか、限定情報を表示するか、他ユーザーの申請であることを示す。 | I33: (none) | J33: P2 | K33: 一部合格 | L33: https://jam.dev/c/af3d194a-5853-473f-87f7-df2e469fe7c3 | M33: It did not show yet the AI hallucinate | N33: Spec 6.5, Spec 6.7 (権限) → "ロールベースアクセス制御: 起案者は自分の申請を編集/閲覧, 承認者は割り当てられた案件を操作, 管理者は全件閲覧し設定変更."
A34: KT-STS-001 | B34: ステータス | C34: 保留中ステータス表示 | D34: カードと詳細の保留中ステータス表示を確認 | E34: メイン | F34: 新規申請を作成直後 | G34: 1. staff@gmail.comでログイン 2. 新規申請 → カテゴリ: Other 3. タイトル: 'Status Test - Pending'、優先度: Low、部署: QA 4. 取引先: 'Test'、支払: 2026-05-01、Cash 5. 期限: 2026-04-30 17:00 6. 理由: 'Testing pending status display'、目的: 'Status verification' 7. 「申請を作成」 8. ダッシュボードでカードを確認 → 詳細をクリック | H34: ダッシュボードカードと詳細表示にオレンジ色の「保留中」バッジ。申請がアクティブリストに表示。 | I34: (none) | J34: P1 | K34: 合格 | L34: same as previous | N34: Spec 6.3, Spec 9 (UI/UX) → "ステータス: Draft / Applying / Waiting for Approval (by stage) / Sent Back / Rejected / Approved / Expired."
A35: KT-STS-002 | B35: ステータス | C35: 承認済みステータス表示 | D35: 管理者承認後の承認済みステータスを確認 | E35: メイン | F35: 管理者が申請を承認 | G35: 1. manager@gmail.comでログイン 2. 'Status Test - Pending'のカードを見つける → 詳細 /approval-requests/[id] 3. 緑の承認ボタン → 確認 4. staff@gmail.comに切り替え 5. ダッシュボードで承認済みカードを見つける 6. クリック → 詳細表示 | H35: カードと詳細に緑色のCheckCircleアイコン付き「承認済み」バッジ。承認情報がタイムラインタブに表示。 | I35: (none) | J35: P1 | K35: 合格 | N35: Spec 6.3, Spec 9 (UI/UX) → "ステータス: Draft / Applying / Waiting for Approval (by stage) / Sent Back / Rejected / Approved / Expired."
A36: KT-STS-003 | B36: ステータス | C36: 却下ステータス表示 | D36: 却下ステータス表示を確認 | E36: 基本 | F36: 管理者が申請を却下 | G36: 1. staff@gmail.comでログイン → 新規申請: 'Status Test - To Be Rejected'、Low、QA（残りを入力） 2. manager@gmail.comに切り替え → 申請を見つけて詳細を開く 3. 赤い却下ボタン → 'Test rejection'を入力 → 確認 4. staff@gmail.comに切り替え → 却下された申請を確認 | H36: 赤色のXCircleアイコン付き「却下済み」バッジ。却下理由'Test rejection'がタイムラインタブに表示。 | I36: (none) | J36: P2 | K36: 合格 | L36: https://jam.dev/c/2b43d3c6-f2ad-4a1d-984e-ee7d4b8bd278 | N36: Spec 6.3, Spec 9 (UI/UX) → "ステータス: Draft / Applying / Waiting for Approval (by stage) / Sent Back / Rejected / Approved / Expired."
A37: KT-STS-004 | B37: ステータス | C37: 要修正ステータス表示 | D37: 要修正ステータス表示を確認 | E37: 基本 | F37: 管理者が修正を依頼 | G37: 1. staff@gmail.comでログイン → 新規申請: 'Status Test - Needs Revision'、Low、QA（残りを入力） 2. manager@gmail.comに切り替え → 申請を見つけて詳細を開く 3. 「修正依頼」 → 'Please add more details about the budget'を入力 → 確認 4. staff@gmail.comに切り替え → 修正依頼の申請を確認 | H37: オレンジ/黄色の「要修正」バッジ。管理者のフィードバックがタイムラインタブに表示。スタッフに編集ボタンあり。 | I37: (none) | J37: P2 | K37: 不合格 | M37: Not implemented? | N37: Spec 6.3, Spec 9 (UI/UX) → "ステータス: Draft / Applying / Waiting for Approval (by stage) / Sent Back / Rejected / Approved / Expired."
A38: KT-STS-005 | B38: ステータス | C38: 取消ステータス表示 | D38: 申請者取消後の取消ステータスを確認 | E38: 基本 | F38: スタッフが自分の申請を取消 | G38: 1. Login staff@gmail.com → New Submission: 'Status Test - To Be Cancelled', Low, QA (fill remaining) 2. Find pending submission on dashboard → detail /approval-requests/[id] 3. Click Cancel (or equivalent withdraw action) 4. 確認する status on dashboard and detail | H38: グレーの「取消済み」バッジ。申請がアクティブ/保留リストに表示されない。追加アクションなし。 | I38: (none) | J38: P2 | K38: 不合格 | M38: Not implemented? | N38: Spec 6.3, Spec 9 (UI/UX) → "ステータス: Draft / Applying / Waiting for Approval (by stage) / Sent Back / Rejected / Approved / Expired."
A39: KT-ROL-001 | B39: ユーザーロール | C39: スタッフが自分の申請を閲覧 | D39: スタッフがダッシュボードで自分の申請のみ閲覧 | E39: メイン | F39: 複数ユーザーが申請を持っている | G39: 1. manager@gmail.comでログイン → 稟議を申請: 'Manager's Test Submission'、Low、Management（未作成の場合） 2. ログアウト → staff@gmail.comでログイン 3. ダッシュボード → 表示されている全申請カードを確認 | H39: スタッフは自分の申請のみ表示。'Manager's Test Submission'は表示されない。他ユーザーの申請なし。 | I39: (none) | J39: P1 | K39: 一部合格 | L39: https://jam.dev/c/c778d93c-439e-47df-9600-95ef39426796 | M39: Client Side (FE side) Bug, after changin the role, the previous role submission still appear | N39: Spec 6.7 (権限), Spec 3 (ステークホルダー) → "ロールベースアクセス制御: 起案者は自分の申請を編集/閲覧, 承認者は割り当てられた案件を操作, 管理者は全件閲覧し設定変更."
A40: KT-ROL-002 | B40: ユーザーロール | C40: 管理者が全件閲覧＋承認可能 | D40: 管理者が全申請を閲覧し承認可能 | E40: メイン | F40: 複数ユーザーの申請が存在 | G40: 1. Login manager@gmail.com 2. Go to dashboard → check visible submission cards 3. Click any pending submission → detail /approval-requests/[id] 4. 利用可能なアクションボタンを確認 | H40: 管理者は全ユーザーの申請を表示。保留中の申請に緑の承認ボタンと赤の却下ボタン。 | I40: (none) | J40: P1 | K40: 不合格 | M40: manager cannot see staff currently | N40: Spec 6.7 (権限), Spec 3 (ステークホルダー) → "ロールベースアクセス制御: 起案者は自分の申請を編集/閲覧, 承認者は割り当てられた案件を操作, 管理者は全件閲覧し設定変更."
A41: KT-ROL-003 | B41: ユーザーロール | C41: スタッフに承認ボタンなし | D41: スタッフに承認/却下ボタンが表示されない | E41: 基本 | F41: 保留中の申請が存在 | G41: 1. staff@gmail.comでログイン 2. 自分の申請をクリック → 詳細 /approval-requests/[id] 3. 利用可能な全アクションボタンを確認 4. ダッシュボードカードのアクションも確認 | H41: 承認、却下、修正依頼ボタンなし。スタッフは: 編集（保留中のみ）、取消（利用可能な場合）、閲覧のみ。 | I41: (none) | J41: P1 | K41: 合格 | N41: Spec 6.7 (権限), Spec 3 (ステークホルダー) → "ロールベースアクセス制御: 起案者は自分の申請を編集/閲覧, 承認者は割り当てられた案件を操作, 管理者は全件閲覧し設定変更."
A42: KT-ROL-004 | B42: ユーザーロール | C42: 管理者のクイック承認 | D42: 管理者がダッシュボードカードからクイック承認 | E42: 基本 | F42: ダッシュボードに保留中の申請 | G42: 1. Login manager@gmail.com 2. Go to dashboard → find pending ringi card 3. を探す quick-action buttons on card 4. If available, use quick-approve | H42: カードにクイック承認あり（実装されている場合）。ダッシュボードからの承認が成功。カードステータスが即座に更新。 | I42: (none) | J42: P2 | K42: 合格 | N42: Spec 6.7 (権限), Spec 3 (ステークホルダー) → "ロールベースアクセス制御: 起案者は自分の申請を編集/閲覧, 承認者は割り当てられた案件を操作, 管理者は全件閲覧し設定変更."
A43: KT-ROL-005 | B43: ユーザーロール | C43: スタッフの管理画面URL直接アクセス | D43: スタッフが管理画面URLに直接アクセス | E43: エッジケース | F43: staff@gmail.comでログイン | G43: 1. staff@gmail.comでログイン 2. URL入力: https://eb-filemg-development.vercel.app/superadmin/dashboard → Enter 3. 結果を確認 4. 同様に試行: https://eb-filemg-development.vercel.app/superadmin/users | H43: スタッフが管理ページにアクセス不可。/ にリダイレクトまたはアクセス拒否。管理機能が公開されない。サイドバーに管理ナビなし。 | I43: (none) | J43: P1 | K43: 合格 | L43: https://jam.dev/c/39a8da64-75f7-4bfa-bdf1-288fce1229be | N43: Spec 6.7 (権限), Spec 3 (ステークホルダー) → "ロールベースアクセス制御: 起案者は自分の申請を編集/閲覧, 承認者は割り当てられた案件を操作, 管理者は全件閲覧し設定変更."
A44: KT-ROL-006 | B44: ユーザーロール | C44: 経理担当者の閲覧専用 | D44: 経理担当者が閲覧のみで操作不可 | E44: エッジケース | F44: 経理担当者ロールが存在 | G44: 1. 確認する accountant test account exists 2. If yes, login with accountant credentials 3. Go to dashboard → navigate to submission detail /approval-requests/[id] 4. 利用可能な操作を確認 | H44: 経理担当者は申請を閲覧可能だが承認/却下/編集不可。アクションボタンなし。閲覧専用アクセス。 | I44: (none) | J44: P3 | K44: 不合格 | L44: https://jam.dev/c/76d1929b-f41c-4138-be8a-b6d24c036407 | M44: empty ringi on accountant | N44: Spec 6.7 (権限), Spec 3 (ステークホルダー) → "ロールベースアクセス制御: 起案者は自分の申請を編集/閲覧, 承認者は割り当てられた案件を操作, 管理者は全件閲覧し設定変更."
A45: KT-AIC-009 | B45: AIチャット | C45: ドキュメントアップロード、AIが申請作成 | D45: チャットで稟議ドキュメントをアップロード、AIがデータ抽出し申請作成 | E45: メイン | F45: staff@gmail.comでログイン | G45: 1. Login staff@gmail.com 2. Go to new chat at / 3. Click paperclip → select ringi_en_form_laptop_purchase.docx 4. 確認する file appears as attachment 5. Type: "Create a submission from this document" 6. Send and wait for response 7. Review extracted data | H45: AIが主要データを抽出（タイトル、金額 ~$6,000、取引先、部署: Engineering）。事前入力された申請を提案。データがドキュメントと一致。 | I45: ringi_en_form_laptop_purchase.docx | J45: P1 | K45: 合格 | L45: https://jam.dev/c/1efadd9c-aaeb-4818-8f43-f1cdaa356980 | N45: Spec 5 (業務フロー), Spec 6.1, Spec 6.4 → "コンテキスト入力支援: チャットメッセージを要約してフォーム初期値を提案."
A46: KT-AIC-010 | B46: AIチャット | C46: チャットで複数ファイルアップロード | D46: AIチャットで複数ファイルを同時にアップロード | E46: 基本 | F46: staff@gmail.comでログイン | G46: 1. Login staff@gmail.com 2. Go to new chat at / 3. Click paperclip → select both: ringi_en_detailed_license_renewal.docx and ringi_en_purchase_monitors.docx 4. 確認する both appear as previews 5. Type: "Please summarize both documents" 6. Send and review response | H46: 両ファイルがアップロードされる。AIが両方を確認。個別の要約: Adobeライセンス/$12,500とDellモニター/$3,750。 | I46: ringi_en_detailed_license_renewal.docx, ringi_en_purchase_monitors.docx | J46: P2 | K46: 一部合格 | L46: https://jam.dev/c/e9294356-f4ce-4bcb-92b1-fa3317f70460 | M46: is it considered as 1 ringi or 2 ringi? can AI smartly categorize between same ringin file or different ringi file? | N46: Spec 6.1, Spec 6.4 → "添付ファイル: Quotes, contracts, and related materials. 承認後の改ざん不可（新バージョンとして再申請が必要）."
A47: KT-AIC-011 | B47: AIチャット | C47: チャットのファイルカード操作 | D47: チャットのファイルカード操作（開く/共有/削除） | E47: 基本 | F47: staff@gmail.comでログイン | G47: 1. staff@gmail.comでログイン 2. / で新規チャットにアクセス 3. ペーパークリップ → ringi_en_form_laptop_purchase.docxを選択 4. 入力: "What is this file about?" 5. 送信して応答を待つ 6. チャット内のファイルカードを確認: アクションボタン（Open、Share） 7. Openをクリック → ファイルが開くことを確認 8. Shareをクリック → リンクがコピーされることを確認 | H47: ファイル名/タイプ付きファイルカードが表示。Openボタンでファイルが開く。Shareボタンで共有リンクがコピー。UIが明確で一貫性がある。 | I47: ringi_en_form_laptop_purchase.docx | J47: P2 | K47: 一部合格 | L47: https://jam.dev/c/23f297ee-bd19-42be-93c5-3d59a25b1c86 | M47: there is bug that the file atteched is 0 even though it is submitted for the requirement it is debatable the test cases perhaps should be updated also why upload through "Drag & drop files here or click to browse - Max 20MB per file - Up to 10 files Supported: PDF, DOCX, XLSX, PPTX, CSV, TXT, MD, JPG, PNG, HEIC, ZIP" have different flow? | N47: Spec 6.4, Spec 9 (UI/UX) → "チャットカードから承認/差戻し."
A48: KT-AIC-012 | B48: AIチャット | C48: AIでアップロード済みファイルを検索 | D48: AIチャットでアップロード済みファイルを検索 | E48: 基本 | F48: staff@gmail.comでログイン、ファイルが以前にアップロード済み | G48: 1. Login staff@gmail.com (files previously uploaded) 2. Go to new chat at / 3. Type: "Find my uploaded documents" 4. Send and review response 5. 確認する SearchResultsCard with file cards | H48: AIが以前にアップロードしたファイルの検索/取得を使用。Open/Shareアクション付きファイルカードのSearchResultsCard。 | I48: (none) | J48: P2 | K48: 合格 | L48: https://jam.dev/c/3572f7bd-7456-4791-8ec0-424054bd2190 | N48: Spec 6.5, Spec 6.4 → "稟議ID、件名、申請者、部門、金額範囲、ステータス、期間で検索/フィルタ."
A49: KT-AIC-013 | B49: AIチャット | C49: クイックアクションカードの使用 | D49: クイックアクションカード「ドキュメントから申請作成」を使用 | E49: 基本 | F49: staff@gmail.comでログイン | G49: 1. staff@gmail.comでログイン 2. / で新規チャット（空の状態）にアクセス 3. 3つのアクションカードを確認: 'Create submission from docs'、'Find approval evidence'、'Review submission status' 4. 'Create submission from docs'をクリック 5. AIプロンプトに従う → ringi_en_form_laptop_purchase.docxをアップロード 6. AIのワークフローを確認 | H49: 3つのアクションカードが全て表示。クリックでAIワークフローが起動。AIがドキュメントアップロードを促す。アップロード後、AIが申請作成を処理。 | I49: (none) | J49: P2 | K49: 合格 | L49: https://jam.dev/c/b29bbd40-08df-40c9-aa35-c1ede9fad64a | N49: Spec 5 (業務フロー), Spec 6.4, Spec 9 (UI/UX) → "起案者がチャットから稟議起案フォームを開き、必要項目と添付を入力して送信."

Sheet Actionable Test Bugs
A1: Bug ID | B1: TC-ID | C1: Category | D1: Bug Title | E1: Description | F1: Type | G1: Severity | H1: Evidence | I1: Status
A2: BUG-001 | B2: KT-SUB-001 | C2: Submission | D2: "Submitted By Staff" shows null | E2: Subtle bug: "Submitted By" field displays null for staff submissions. The submitter name is not populated correctly. | F2: Bug | G2: Major | H2: https://jam.dev/c/c59ad198-fb75-4953-8e4c-279d811bdcc1 | I2: Open
A3: BUG-002 | B3: KT-SUB-001 | C3: Submission | D3: No Draft submission status (spec requires it) | E3: System lacks Draft submission status. Spec requires a Draft state before Pending, allowing users to save incomplete submissions. | F3: Enhancement | G3: Minor | H3: https://jam.dev/c/c59ad198-fb75-4953-8e4c-279d811bdcc1 | I3: Open
A4: BUG-003 | B4: KT-SUB-002 | C4: Submission | D4: Tax number display incorrect in form and details | E4: Subtle bug regarding the tax number in both the submission form and the details view. Tax calculation or display is incorrect. | F4: Bug | G4: Major | H4: https://jam.dev/c/e7c5d836-7e67-4e76-82d7-9d8f3957ce0d | I4: Open
A5: BUG-004 | B5: KT-SUB-003 | C5: Submission | D5: File click in detail shows XML instead of file | E5: When clicking on an attached file in the submission detail view, it displays raw XML content instead of the actual file or a proper preview. | F5: Bug | G5: Major | H5: https://jam.dev/c/e5777a3f-6626-4419-92d8-8884a9ef544d | I5: Open
A6: BUG-005 | B6: KT-SUB-009 | C6: Submission | D6: Upload fails for filename with special/JP chars | E6: File upload fails or errors when the filename contains special characters or Japanese characters (e.g., edge_special_chars_名前.docx). | F6: Bug | G6: Major | H6: https://jam.dev/c/e9e24876-69bd-4c41-ba8b-0886be4cd867 | I6: Open
A7: BUG-006 | B7: KT-SUB-010 | C7: Submission | D7: Number overflow on very large amount | E7: Number overflow occurs when entering very large monetary amounts (e.g., $999,999,999,999). The system does not handle large numbers gracefully. | F7: Bug | G7: Minor | H7: https://jam.dev/c/e7cb4064-6b39-4b65-a1e8-e609eef7f6e5 | I7: Open
A8: BUG-007 | B8: KT-APR-001 | C8: Approval | D8: Approval status glitch — shows empty status | E8: Approval status glitches: shows status briefly then becomes empty. Workaround: login as staff first, logout, then login as manager. | F8: Bug | G8: Critical | H8: https://jam.dev/c/432754ce-879c-4937-a5a1-f315125385af | I8: Open
A9: BUG-008 | B9: KT-AIC-001 | C9: AI Chat | D9: AI creates submission as Pending instead of Draft | E9: AI generates ringi with Pending status instead of Draft. This prevents the user from editing the ringi before formal submission. | F9: Bug | G9: Critical | H9: https://jam.dev/c/3ff23937-7197-4d13-9381-65ef837e3113 | I9: Open
A10: BUG-009 | B10: KT-AIC-001 | C10: AI Chat | D10: Edit ringi from AI-created submission has bugs | E10: When user tries to edit an AI-created ringi submission, the edit form has bugs and does not function correctly. | F10: Bug | G10: Major | H10: https://jam.dev/c/3ff23937-7197-4d13-9381-65ef837e3113 | I10: Open
A11: BUG-010 | B11: KT-AIC-002 | C11: AI Chat | D11: AI asks same questions repeatedly in JP flow | E11: In Japanese language flow, AI keeps asking the same questions again and again instead of progressing the conversation. | F11: Bug | G11: Major | H11: https://jam.dev/c/37d7d204-3527-4e40-aad0-e51fab33d42a | I11: Open
A12: BUG-011 | B12: KT-AIC-004 | C12: AI Chat | D12: UI glitch and loader not appearing during AI response | E12: UI glitch occurs during AI processing. The loading indicator does not appear while waiting for AI response. | F12: Bug | G12: Minor | H12: https://jam.dev/c/40723d7b-aae3-47e5-81e3-d83304091945 | I12: Open
... A22: BUG-021 | B22: KT-AIR-006 | C22: AI Retrieval | D22: AI hallucinates data for other user's submission | E22: AI does not show the requested submission but instead hallucinates/fabricates data about another user's submission. | F22: Bug | G22: Critical | H22: https://jam.dev/c/af3d194a-5853-473f-87f7-df2e469fe7c3 | I22: Open
A23: BUG-022 | B23: KT-STS-004 | C23: Status | D23: Request Revision feature not implemented | E23: The Request Revision (send-back) workflow is not implemented. Manager cannot request changes from the submitter. | F23: Bug | G23: Critical | I23: Open
A24: BUG-023 | B24: KT-STS-005 | C24: Status | D24: Cancel submission feature not implemented | E24: The Cancel submission feature is not implemented. Submitter cannot cancel their own pending submission. | F24: Bug | G24: Critical | I24: Open
A25: BUG-024 | B25: KT-ROL-001 | C25: User Role | D25: Previous role's submissions still visible after role change (FE cache bug) | E25: Client-side (frontend) cache bug: after changing a user's role, the previous role's submissions still appear in the dashboard until hard refresh. | F25: Bug | G25: Major | H25: https://jam.dev/c/c778d93c-439e-47df-9600-95ef39426796 | I25: Open
A26: BUG-025 | B26: KT-ROL-002 | C26: User Role | D26: Manager cannot see staff submissions | E26: Manager role cannot see staff submissions on the dashboard. Staff-submitted ringi are not visible to the manager. | F26: Bug | G26: Critical | I26: Open
A27: BUG-026 | B27: KT-ROL-006 | C27: User Role | D27: Accountant sees empty ringi list | E27: Accountant role sees an empty ringi list. No submissions are displayed even though they should have read access. | F27: Bug | G27: Major | H27: https://jam.dev/c/76d1929b-f41c-4138-be8a-b6d24c036407 | I27: Open
A28: BUG-027 | B28: KT-AIC-010 | C28: AI Chat | D28: AI cannot differentiate between multiple uploaded ringi files | E28: When multiple ringi files are uploaded, AI cannot distinguish whether they represent 1 submission or 2 separate submissions. | F28: Enhancement | G28: Minor | H28: https://jam.dev/c/e9294356-f4ce-4bcb-92b1-fa3317f70460 | I28: Open
A29: BUG-028 | B29: KT-AIC-011 | C29: AI Chat | D29: File attachment count shows 0 despite file being submitted | E29: File attachment count displays 0 even though a file was successfully submitted. The attachment metadata is not updated correctly. | F29: Bug | G29: Major | H29: https://jam.dev/c/23f297ee-bd19-42be-93c5-3d59a25b1c86 | I29: Open

Sheet 実行可能テストバグ
A1: バグID | B1: TC-ID | C1: カテゴリ | D1: バグタイトル | E1: 説明 | F1: タイプ | G1: 重要度 | H1: エビデンス | I1: ステータス
A2: BUG-001 | B2: KT-SUB-001 | C2: 申請 | D2: 「申請者: スタッフ」がnullを表示 | E2: 微妙なバグ: 「申請者」フィールドがスタッフの申請でnullを表示。申請者名が正しく取得されていない。 | F2: バグ | G2: 重要 | H2: https://jam.dev/c/c59ad198-fb75-4953-8e4c-279d811bdcc1 | I2: 未対応
A3: BUG-002 | B3: KT-SUB-001 | C3: 申請 | D3: 下書きステータスがない（仕様では必要） | E3: システムに下書きステータスがない。仕様では保留中の前に下書き状態が必要で、未完成の申請を保存可能にする。 | F3: 改善提案 | G3: 軽微 | H3: https://jam.dev/c/c59ad198-fb75-4953-8e4c-279d811bdcc1 | I3: 未対応
A4: BUG-003 | B4: KT-SUB-002 | C4: 申請 | D4: フォームと詳細で税番号の表示が不正 | E4: 申請フォームと詳細ビューの両方で税番号に関する微妙なバグ。税計算または表示が不正確。 | F4: バグ | G4: 重要 | H4: https://jam.dev/c/e7c5d836-7e67-4e76-82d7-9d8f3957ce0d | I4: 未対応
A5: BUG-004 | B5: KT-SUB-003 | C5: 申請 | D5: 詳細でファイルクリック時にXMLが表示される | E5: 申請詳細ビューで添付ファイルをクリックすると、実際のファイルではなくXMLコンテンツが表示される。 | F5: バグ | G5: 重要 | H5: https://jam.dev/c/e5777a3f-6626-4419-92d8-8884a9ef544d | I5: 未対応
A6: BUG-005 | B6: KT-SUB-009 | C6: 申請 | D6: 特殊文字/日本語文字のファイル名でアップロード失敗 | E6: ファイル名に特殊文字や日本語文字が含まれている場合、アップロードが失敗またはエラーが発生。 | F6: バグ | G6: 重要 | H6: https://jam.dev/c/e9e24876-69bd-4c41-ba8b-0886be4cd867 | I6: 未対応
A7: BUG-006 | B7: KT-SUB-010 | C7: 申請 | D7: 非常に大きな金額で数値オーバーフロー | E7: 非常に大きな金額（例: $999,999,999,999）を入力すると数値オーバーフローが発生。 | F7: バグ | G7: 軽微 | H7: https://jam.dev/c/e7cb4064-6b39-4b65-a1e8-e609eef7f6e5 | I7: 未対応
A8: BUG-007 | B8: KT-APR-001 | C8: 承認 | D8: 承認ステータスの不具合 — ステータスが空になる | E8: 承認ステータスが一瞬表示された後空になる不具合。回避策: 先にスタッフでログイン、ログアウト、その後マネージャーでログイン。 | F8: バグ | G8: 重大 | H8: https://jam.dev/c/432754ce-879c-4937-a5a1-f315125385af | I8: 未対応
A9: BUG-008 | B9: KT-AIC-001 | C9: AIチャット | D9: AIが下書きではなく保留中として申請を作成 | E9: AIが下書きではなく保留中ステータスで稿議を生成。ユーザーが正式申請前に稿議を編集できない。 | F9: バグ | G9: 重大 | H9: https://jam.dev/c/3ff23937-7197-4d13-9381-65ef837e3113 | I9: 未対応
A10: BUG-009 | B10: KT-AIC-001 | C10: AIチャット | D10: AI作成の稿議編集にバグあり | E10: AIが作成した稿議申請を編集しようとすると、編集フォームにバグがあり正常に動作しない。 | F10: バグ | G10: 重要 | H10: https://jam.dev/c/3ff23937-7197-4d13-9381-65ef837e3113 | I10: 未対応
A11: BUG-010 | B11: KT-AIC-002 | C11: AIチャット | D11: AIが日本語フローで同じ質問を繰り返す | E11: 日本語フローでAIが会話を進めずに同じ質問を繰り返し続ける。 | F11: バグ | G11: 重要 | H11: https://jam.dev/c/37d7d204-3527-4e40-aad0-e51fab33d42a | I11: 未対応
A12: BUG-011 | B12: KT-AIC-004 | C12: AIチャット | D12: UI不具合とAI応答中にローダーが表示されない | E12: AI処理中にUI不具合が発生。AI応答待ち中にローディングインジケーターが表示されない。 | F12: バグ | G12: 軽微 | H12: https://jam.dev/c/40723d7b-aae3-47e5-81e3-d83304091945 | I12: 未対応
... A22: BUG-021 | B22: KT-AIR-006 | C22: AI検索 | D22: AIが他のユーザーの申請データを捜造する | E22: AIが要求された申請を表示せず、他のユーザーの申請についてデータを捜造/ハルシネーションする。 | F22: バグ | G22: 重大 | H22: https://jam.dev/c/af3d194a-5853-473f-87f7-df2e469fe7c3 | I22: 未対応
A23: BUG-022 | B23: KT-STS-004 | C23: ステータス | D23: 修正依頼機能が未実装 | E23: 修正依頼（差戳し）ワークフローが未実装。マネージャーが申請者に変更を要求できない。 | F23: バグ | G23: 重大 | I23: 未対応
A24: BUG-023 | B24: KT-STS-005 | C24: ステータス | D24: 申請取消機能が未実装 | E24: 申請取消機能が未実装。申請者が自分の保留中の申請を取り消せない。 | F24: バグ | G24: 重大 | I24: 未対応
A25: BUG-024 | B25: KT-ROL-001 | C25: ユーザーロール | D25: ロール変更後に前のロールの申請が表示される（FEキャッシュバグ） | E25: クライアントサイド（フロントエンド）のキャッシュバグ: ロール変更後、ハードリフレッシュまで前のロールの申請がダッシュボードに表示される。 | F25: バグ | G25: 重要 | H25: https://jam.dev/c/c778d93c-439e-47df-9600-95ef39426796 | I25: 未対応
A26: BUG-025 | B26: KT-ROL-002 | C26: ユーザーロール | D26: マネージャーがスタッフの申請を見れない | E26: マネージャーロールがダッシュボードでスタッフの申請を見ることができない。 | F26: バグ | G26: 重大 | I26: 未対応
A27: BUG-026 | B27: KT-ROL-006 | C27: ユーザーロール | D27: 経理担当者の稿議リストが空 | E27: 経理担当者ロールが空の稿議リストを表示。読み取りアクセスがあるはずの申請が表示されない。 | F27: バグ | G27: 重要 | H27: https://jam.dev/c/76d1929b-f41c-4138-be8a-b6d24c036407 | I27: 未対応
A28: BUG-027 | B28: KT-AIC-010 | C28: AIチャット | D28: AIが複数アップロードの稿議ファイルを区別できない | E28: 複数の稿議ファイルをアップロードした場合、AIが1件の申請か2件の別々の申請かを区別できない。 | F28: 改善提案 | G28: 軽微 | H28: https://jam.dev/c/e9294356-f4ce-4bcb-92b1-fa3317f70460 | I28: 未対応
A29: BUG-028 | B29: KT-AIC-011 | C29: AIチャット | D29: ファイルが送信されているのに添付ファイル数が0を表示 | E29: ファイルが正常に送信されたにもかかわらず、添付ファイル数が0を表示。添付メタデータが正しく更新されていない。 | F29: バグ | G29: 重要 | H29: https://jam.dev/c/23f297ee-bd19-42be-93c5-3d59a25b1c86 | I29: 未対応
